Workbook

Sheet ✈ Flights
A1: ✈ AIRLINE DATASET — FLIGHTS TABLE (Contains Dirty Data)
A2: Flight Id | B2: Flight Date | C2: Airline | D2: Origin City | E2: Origin Code | F2: Destination City | G2: Destination Code | H2: Departure Time | I2: Arrival Time | J2: Flight Duration Min | K2: Distance Miles | L2: Ticket Price | M2: Class | N2: Seats Available | O2: Passengers Boarded | P2: Status | Q2: Delay Minutes
A3: FL001 | B3: 2022-08-17 | C3: Delta | D3: Boston | E3: BOS | F3: Denver | G3: DEN | H3: 07:15 | I3: 15:02 | J3: 467 | K3: 719 | L3: 837.9 | M3: First Class | N3: 122 | O3: 104 | P3: On-Time | Q3: 0
A4: FL002 | B4: 2022-07-11 | C4: Southwest | D4: Denver | E4: DEN | F4: Orlando | G4: MCO | H4: 19:00 | I4: 01:17 | J4: 377 | K4: 1114 | L4: 881.94 | M4: First Class | N4: 239 | O4: 157 | P4: On-Time | Q4: 0
A5: FL003 | B5: 2023-07-24 | C5: Delta | D5: Miami | E5: MIA | F5: Charlotte | G5: CLT | H5: 10:30 | I5: 13:19 | J5: 169 | K5: 1181 | L5: 1152.08 | M5: Business | N5: 126 | O5: 61 | P5: On-Time | Q5: 0
A6: FL004 | B6: 2024-01-06 | C6: Alaska | D6: San Diego | E6: SAN | F6: Boston | G6: BOS | H6: 01:45 | I6: 07:49 | J6: 364 | K6: 811 | L6: 1169.89 | M6: Business | N6: 120 | O6: 120 | P6: On-Time | Q6: 0
A7: FL005 | B7: 2024-01-11 | C7: Southwest | D7: Chicago | E7: ORD | F7: Los Angeles | G7: LAX | H7: 21:15 | I7: 01:13 | J7: 238 | K7: 626 | L7: 1037.96 | M7: Economy | N7: 197 | O7: 121 | P7: On-Time | Q7: 0
A8: FL006 | B8: 2024-01-18 | C8: American | D8: San Francisco | E8: SFO | F8: Minneapolis | G8: MSP | H8: 06:30 | I8: 13:59 | J8: 449 | K8: 2954 | L8: 159.97 | M8: First Class | N8: 143 | O8: 118 | P8: Delayed | Q8: 56
A9: FL007 | B9: 2024-08-04 | C9: Spirit | D9: Boston | E9: BOS | F9: Chicago | G9: MDW | H9: 07:30 | I9: 09:28 | J9: 118 | K9: 1238 | L9: 1000.42 | M9: Business | N9: 202 | O9: 118 | P9: On-Time | Q9: 0
A10: FL008 | B10: 2023-10-07 | C10: Southwest | D10: Newark | E10: EWR | F10: Minneapolis | G10: MSP | H10: 20:45 | I10: 23:28 | J10: 163 | K10: 1384 | L10: 236.39 | M10: First Class | N10: 243 | O10: 187 | P10: On-Time | Q10: 0
A11: FL009 | B11: 2024-05-27 | C11: spirit | D11: San Francisco | E11: SFO | F11: Denver | G11: DEN | H11: 04:45 | I11: 07:01 | J11: 136 | K11: 492 | L11: 1044.44 | M11: Economy | N11: 260 | O11: 90 | P11: Delayed | Q11: 123
A12: FL010 | B12: 2022-05-11 | C12: Spirit | D12: Minneapolis | E12: MSP | F12: Newark | G12: EWR | H12: 16:30 | I12: 22:43 | J12: 373 | K12: 347 | M12: Economy | N12: 274 | O12: 187 | P12: Delayed | Q12: 179
A13: FL011 | B13: 2023-11-28 | C13: United | D13: Las Vegas | E13: LAS | F13: Charlotte | G13: CLT | H13: 05:45 | I13: 07:16 | J13: 91 | K13: 1378 | L13: 1168.51 | M13: Economy | N13: 229 | O13: 77 | P13: Delayed | Q13: 91
A14: FL012 | B14: 2024-11-05 | C14: Southwest | D14: Dallas | E14: DFW | F14: Minneapolis | G14: MSP | H14: 05:00 | I14: 11:36 | J14: 396 | K14: 1627 | L14: 627.24 | M14: Economy | N14: 337 | O14: 235 | P14: Delayed | Q14: 93
A15: FL013 | B15: 2023-05-06 | C15: Delta | D15: Denver | E15: DEN | F15: San Diego | G15: SAN | H15: 02:00 | I15: 09:44 | J15: 464 | K15: 2290 | L15: 993.95 | M15: First Class | N15: 296 | O15: 82 | P15: On-Time | Q15: 0
A16: FL014 | B16: 2024-08-31 | C16: American | D16: Boston | E16: BOS | F16: Orlando | G16: MCO | H16: 19:45 | I16: 23:03 | J16: 198 | K16: 2508 | L16: 925.9 | M16: First Class | N16: 151 | O16: 141 | P16: On-Time | Q16: 0
A17: FL015 | B17: 2024-02-04 | C17: Frontier | D17: Houston | E17: IAH | F17: Charlotte | G17: CLT | H17: 03:15 | I17: 06:40 | J17: 205 | K17: 562 | L17: 458.66 | M17: First Class | N17: 241 | O17: 108 | P17: On-Time | Q17: 0
A18: FL016 | B18: 2022-01-15 | C18: United | D18: Los Angeles | E18: LAX | F18: Boston | G18: BOS | H18: 02:00 | I18: 06:19 | J18: 259 | K18: 590 | L18: 655.85 | M18: Business | N18: 271 | O18: 174 | P18: On-Time | Q18: 0
A19: FL017 | B19: 2022-09-28 | C19: Frontier | D19: Denver | E19: DEN | F19: Houston | G19: IAH | H19: 13:15 | I19: 15:33 | J19: 138 | K19: 697 | L19: 818.06 | M19: Business | N19: 208 | O19: 155 | P19: On-Time | Q19: 0
A20: FL018 | B20: 2022-04-21 | C20: United | D20: Los Angeles | E20: LAX | F20: Detroit | G20: DTW | H20: 23:30 | I20: 01:55 | J20: 145 | K20: 1318 | L20: 294.58 | M20: First Class | N20: 214 | O20: 85 | P20: On-Time | Q20: 0
A21: FL019 | B21: 2023-07-25 | C21: Frontier | D21: Denver | E21: DEN | F21: Chicago | G21: ORD | H21: 14:00 | I21: 15:55 | J21: 115 | K21: 2971 | L21: 1199.2 | M21: Economy | N21: 348 | O21: 97 | P21: Delayed | Q21: 75
A22: FL020 | B22: 2022-12-07 | C22: Spirit | D22: Newark | E22: EWR | F22: Houston | G22: IAH | H22: 06:45 | I22: 08:45 | J22: 120 | K22: 974 | L22: 504.45 | M22: Business | N22: 167 | O22: 150 | P22: Delayed | Q22: 88
A23: FL021 | B23: 2024-05-16 | C23: Frontier | D23: Dallas | E23: DFW | F23: Denver | G23: DEN | H23: 09:15 | I23: 11:14 | J23: 119 | K23: 2672 | L23: 904.03 | M23: Economy | N23: 291 | O23: 130 | P23: On-Time | Q23: 0
A24: FL022 | B24: 2024-09-03 | C24: American | D24: Los Angeles | E24: LAX | F24: Orlando | G24: MCO | H24: 02:15 | I24: 04:20 | J24: 125 | K24: 2737 | L24: 156.12 | M24: Economy | N24: 203 | O24: 80 | P24: Cancelled | Q24: 0
... A29: FL027 | B29: 2023-06-25 | C29: Frontier | D29: Boston | E29: BOS | F29: Los Angeles | G29: LAX | H29: 02:45 | I29: 06:36 | J29: 231 | K29: 480 | L29: 83.97 | M29: Economy | N29: 263 | O29: 117 | P29: On-Time | Q29: 0
A30: FL028 | B30: 2024-06-23 | C30: Spirit | D30: Orlando | E30: MCO | F30: New York | G30: JFK | H30: 03:00 | I30: 10:23 | J30: 443 | K30: 910 | L30: 691.06 | M30: Business | N30: 249 | P30: On-Time | Q30: 0
A31: FL029 | B31: 2022-09-19 | C31: Delta | D31: Las Vegas | E31: LAS | F31: Minneapolis | G31: MSP | H31: 01:30 | I31: 04:47 | J31: 197 | K31: 1322 | L31: 826.97 | M31: Business | N31: 299 | O31: 193 | P31: Delayed | Q31: 119
A32: FL030 | B32: 2022-11-13 | C32: Southwest | D32: Miami | E32: MIA | F32: Seattle | G32: SEA | H32: 13:00 | I32: 16:01 | J32: 181 | K32: 1660 | L32: 956.27 | M32: Business | N32: 305 | O32: 177 | P32: On-Time | Q32: 0
A33: FL031 | B33: 2022-08-10 | C33: Spirit | D33: Los Angeles | E33: LAX | F33: Houston | G33: IAH | H33: 07:15 | I33: 12:40 | J33: 325 | K33: 1732 | M33: Economy | N33: 157 | O33: 53 | P33: Delayed | Q33: 117
A34: FL032 | B34: 2023-11-04 | C34: JetBlue | D34: Chicago | E34: ORD | F34: Las Vegas | G34: LAS | H34: 11:45 | I34: 19:02 | J34: 437 | K34: 2496 | L34: 450.89 | M34: Economy | N34: 129 | O34: 83 | P34: On-Time | Q34: 0
A35: FL033 | B35: 2023-06-28 | C35: Delta | D35: Atlanta | E35: ATL | F35: Charlotte | G35: CLT | H35: 11:30 | I35: 16:43 | J35: 313 | K35: 2783 | L35: 1182.34 | M35: Economy | N35: 198 | O35: 197 | P35: On-Time | Q35: 0
A36: FL034 | B36: 2022-04-01 | C36: Spirit | D36: New York | E36: JFK | F36: Orlando | G36: MCO | H36: 17:15 | I36: 21:51 | J36: 276 | K36: 2066 | L36: 158.37 | M36: First Class | N36: 335 | O36: 219 | P36: On-Time | Q36: -10
A37: FL035 | B37: 2022-09-13 | C37: JetBlue | D37: Houston | E37: IAH | F37: Las Vegas | G37: LAS | H37: 21:45 | I37: 02:02 | J37: 257 | K37: 1948 | L37: 860.87 | M37: First Class | N37: 132 | O37: 74 | P37: On-Time | Q37: 0
A38: FL036 | B38: 2024-02-16 | C38: American | D38: San Diego | E38: SAN | F38: Chicago | G38: MDW | H38: 09:45 | I38: 15:55 | J38: 370 | K38: 301 | L38: 420.34 | M38: Economy | N38: 210 | O38: 198 | P38: On-Time | Q38: 0
A39: FL037 | B39: 2023-10-22 | C39: Frontier | D39: Charlotte | E39: CLT | F39: Newark | G39: EWR | H39: 21:15 | I39: 03:06 | J39: 351 | K39: 2238 | L39: 968.98 | M39: First Class | N39: 143 | O39: 134 | P39: On-Time | Q39: 0
A40: FL038 | B40: 2024-11-21 | C40: Alaska | D40: Chicago | E40: ORD | F40: Boston | G40: BOS | H40: 21:30 | I40: 00:55 | J40: 205 | K40: 1115 | L40: 245.04 | M40: Economy | N40: 162 | O40: 110 | P40: On-Time | Q40: 0
A41: FL039 | B41: 2022-05-30 | C41: Frontier | D41: Detroit | E41: DTW | F41: San Diego | G41: SAN | H41: 06:45 | I41: 12:28 | J41: 343 | K41: 1936 | L41: 353.26 | M41: First Class | N41: 276 | O41: 51 | P41: Delayed | Q41: 42
A42: FL040 | B42: 2024-05-20 | C42: Southwest | D42: Miami | E42: MIA | F42: Orlando | G42: MCO | H42: 14:00 | I42: 20:15 | J42: 375 | K42: 1320 | L42: 1107.57 | M42: Economy | N42: 216 | O42: 84 | P42: Delayed | Q42: 150
A43: FL041 | B43: 2023-10-12 | C43: Frontier | D43: San Diego | E43: SAN | F43: Houston | G43: IAH | H43: 13:45 | I43: 16:36 | J43: 171 | K43: 2244 | L43: 584.08 | M43: Economy | N43: 315 | O43: 191 | P43: Delayed | Q43: 148
A44: FL042 | B44: 2024-09-19 | C44: Southwest | D44: Boston | E44: BOS | F44: Newark | G44: EWR | H44: 02:30 | I44: 06:00 | J44: 210 | K44: 1412 | L44: 456.15 | M44: First Class | N44: 120 | O44: 67 | P44: On-Time | Q44: 0
A45: FL043 | B45: 2024-02-24 | C45: American | D45: Seattle | E45: SEA | F45: Chicago | G45: ORD | H45: 13:45 | I45: 18:04 | J45: 259 | K45: 2522 | L45: 601.84 | N45: 152 | O45: 103 | P45: On-Time | Q45: 0
A46: FL044 | B46: 2022-02-10 | C46: Spirit | D46: Newark | E46: EWR | F46: New York | G46: JFK | H46: 11:30 | I46: 19:25 | J46: 475 | K46: 1897 | L46: 1035.86 | M46: Business | N46: 237 | O46: 189 | P46: Delayed | Q46: 71
A47: FL045 | B47: 2024-09-26 | C47: Southwest | D47: Boston | E47: BOS | F47: Charlotte | G47: CLT | H47: 15:00 | I47: 19:49 | J47: 289 | K47: 1676 | L47: 829.14 | M47: Business | N47: 285 | O47: 92 | P47: Delayed | Q47: 47
A48: FL046 | B48: 2024-12-29 | C48: Delta | D48: Minneapolis | E48: MSP | F48: San Diego | G48: SAN | H48: 18:00 | I48: 20:12 | J48: 132 | K48: 2932 | L48: 560.05 | M48: Business | N48: 146 | O48: 56 | P48: On-Time | Q48: 0
A49: FL047 | B49: 2023-11-02 | C49: Southwest | D49: Charlotte | E49: CLT | F49: Phoenix | G49: PHX | H49: 10:45 | I49: 14:37 | J49: 232 | K49: 2026 | L49: 362.54 | M49: Economy | N49: 220 | O49: 54 | P49: Delayed | Q49: 28
A50: FL048 | B50: 2023-12-18 | C50: Southwest | D50: Chicago | E50: ORD | F50: Los Angeles | G50: LAX | H50: 00:15 | I50: 03:27 | J50: 192 | K50: 383 | L50: 775.9 | N50: 132 | P50: Delayed | Q50: 159
A51: FL049 | B51: 2023-03-23 | C51: Frontier | D51: Boston | E51: BOS | F51: Minneapolis | G51: MSP | H51: 05:00 | I51: 07:53 | J51: 173 | K51: 1574 | L51: 201.07 | M51: Economy | N51: 337 | O51: 209 | P51: On-Time | Q51: 0
A52: FL050 | B52: 2024-02-08 | C52: Spirit | D52: Seattle | E52: SEA | F52: Chicago | G52: ORD | H52: 18:15 | I52: 20:37 | J52: 142 | K52: 1535 | L52: 1032.33 | M52: First Class | N52: 306 | O52: 111 | P52: Delayed | Q52: 159
A53: FL051 | B53: 2022-03-26 | C53: Alaska | D53: Orlando | E53: MCO | F53: Detroit | G53: DTW | H53: 21:30 | I53: 23:35 | J53: 125 | K53: 2372 | L53: 805.25 | M53: Economy | N53: 317 | O53: 265 | P53: Delayed | Q53: 42
A54: FL052 | B54: 2024-06-06 | C54: Alaska | D54: Charlotte | E54: CLT | F54: Dallas | G54: DFW | H54: 13:15 | I54: 21:00 | J54: 465 | K54: 2437 | L54: 1161.33 | M54: Business | N54: 257 | O54: 256 | P54: Delayed | Q54: 138
A55: FL053 | B55: 2024-08-10 | C55: Spirit | D55: Chicago | E55: MDW | F55: Boston | G55: BOS | H55: 10:15 | I55: 12:29 | J55: 134 | K55: 1442 | L55: 1067.43 | M55: Economy | N55: 292 | O55: 168 | P55: On-Time | Q55: 0
A56: FL054 | B56: 2024-02-16 | C56: Alaska | D56: New York | E56: JFK | F56: Houston | G56: IAH | H56: 10:15 | I56: 15:54 | J56: 339 | K56: 1168 | L56: 477.4 | M56: Business | N56: 187 | O56: 121 | P56: Delayed | Q56: 85
A57: FL055 | B57: 2022-01-21 | C57: Southwest | D57: Chicago | E57: ORD | F57: Boston | G57: BOS | H57: 23:45 | I57: 05:25 | J57: 340 | K57: 2574 | L57: 929.14 | M57: First Class | N57: 221 | O57: 215 | P57: Delayed | Q57: 129
A58: FL056 | B58: 2022-02-05 | C58: United | D58: Las Vegas | E58: LAS | F58: Denver | G58: DEN | H58: 12:15 | I58: 16:21 | J58: 246 | K58: 2682 | L58: 493.3 | M58: First Class | N58: 235 | O58: 138 | P58: On-Time | Q58: 0
A59: FL057 | B59: 2023-11-09 | C59: Alaska | D59: Charlotte | E59: CLT | F59: Boston | G59: BOS | H59: 09:30 | I59: 12:58 | J59: 208 | K59: 794 | L59: 887.84 | N59: 130 | O59: 118 | P59: Cancelled | Q59: 0
A60: FL058 | B60: 2023-01-15 | C60: Southwest | D60: Seattle | E60: SEA | F60: Houston | G60: IAH | H60: 08:30 | I60: 10:51 | J60: 141 | K60: 1095 | L60: 411.8 | M60: Business | N60: 145 | O60: 88 | P60: On-Time | Q60: 0
A61: FL059 | B61: 2024-12-29 | C61: American | D61: Boston | E61: BOS | F61: Los Angeles | G61: LAX | H61: 01:30 | I61: 08:57 | J61: 447 | K61: 817 | L61: 794.41 | M61: Business | N61: 126 | O61: 51 | P61: On-Time | Q61: 0
A62: FL060 | B62: 2024-08-19 | C62: Frontier | D62: Charlotte | E62: CLT | F62: Phoenix | G62: PHX | H62: 05:00 | I62: 08:39 | J62: 219 | K62: 2256 | L62: 207.78 | M62: Economy | N62: 202 | O62: 175 | P62: On-Time | Q62: 0
A63: FL061 | B63: 2022-04-20 | C63: American | D63: Dallas | E63: DFW | F63: San Diego | G63: SAN | H63: 09:00 | I63: 12:37 | J63: 217 | K63: 785 | L63: 705.04 | M63: Business | N63: 255 | O63: 202 | P63: Delayed | Q63: 72
A64: FL062 | B64: 2024-12-06 | C64: Spirit | D64: Charlotte | E64: CLT | F64: Newark | G64: EWR | H64: 09:45 | I64: 13:51 | J64: 246 | K64: 2629 | L64: 775.55 | M64: First Class | N64: 345 | O64: 100 | P64: Cancelled | Q64: 0
A65: FL063 | B65: 2023-03-02 | C65: Southwest | D65: Boston | E65: BOS | F65: Chicago | G65: ORD | H65: 05:15 | I65: 08:13 | J65: 178 | K65: 2560 | L65: 164.07 | M65: Economy | N65: 204 | O65: 165 | P65: Delayed | Q65: 135
A66: FL064 | B66: 2023-08-20 | C66: Delta | D66: Denver | E66: DEN | F66: Phoenix | G66: PHX | H66: 22:30 | I66: 05:59 | J66: 449 | K66: 2159 | L66: 159.72 | M66: Economy | N66: 336 | O66: 185 | P66: Delayed | Q66: 175
A67: FL065 | B67: 2023-02-10 | C67: Spirit | D67: Atlanta | E67: ATL | F67: Chicago | G67: MDW | H67: 07:15 | I67: 11:01 | J67: 226 | K67: 882 | L67: 159.98 | M67: Economy | N67: 302 | O67: 128 | P67: On-Time | Q67: 0
A68: FL066 | B68: 2023-08-15 | C68: Frontier | D68: Atlanta | E68: ATL | F68: Newark | G68: EWR | H68: 22:30 | I68: 05:58 | J68: 448 | K68: 1948 | L68: 1135.8 | M68: First Class | N68: 238 | O68: 176 | P68: On-Time | Q68: 0
A69: FL067 | B69: 2022-03-23 | C69: Spirit | D69: Phoenix | E69: PHX | F69: Boston | G69: BOS | H69: 00:00 | I69: 03:27 | J69: 207 | K69: 2656 | L69: 737.58 | M69: Economy | N69: 295 | O69: 222 | P69: Delayed
A70: FL068 | B70: 2022-03-24 | C70: American | D70: Newark | E70: EWR | F70: Orlando | G70: MCO | H70: 20:45 | I70: 00:37 | J70: 232 | K70: 1043 | L70: 1196.58 | M70: Business | N70: 262 | O70: 258 | P70: On-Time | Q70: -10
A71: FL069 | B71: 2022-07-06 | C71: Frontier | D71: San Francisco | E71: SFO | F71: Charlotte | G71: CLT | H71: 10:30 | I71: 17:43 | J71: 433 | K71: 728 | M71: Business | N71: 205 | O71: 176 | P71: On-Time | Q71: 0
A72: FL070 | B72: 2024-03-31 | C72: Delta | D72: Charlotte | E72: CLT | F72: Chicago | G72: ORD | H72: 10:30 | I72: 14:45 | J72: 255 | K72: 774 | L72: 1166.61 | M72: Business | N72: 321 | O72: 313 | P72: Delayed | Q72: 15
A73: FL071 | B73: 2024-08-04 | C73: Spirit | D73: Los Angeles | E73: LAX | F73: Denver | G73: DEN | H73: 16:30 | I73: 23:18 | J73: 408 | K73: 2341 | L73: 780.46 | M73: Economy | N73: 152 | O73: 84 | P73: On-Time | Q73: 0
A74: FL072 | B74: 2023-08-13 | C74: Frontier | D74: Newark | E74: EWR | F74: Atlanta | G74: ATL | H74: 00:15 | I74: 07:48 | J74: 453 | K74: 948 | L74: 428.04 | M74: Economy | N74: 241 | O74: 154 | P74: On-Time | Q74: 0
A75: FL073 | B75: 2022-08-21 | C75: Frontier | D75: Atlanta | E75: ATL | F75: Miami | G75: MIA | H75: 15:30 | I75: 21:20 | J75: 350 | K75: 1419 | L75: 545.35 | M75: Business | N75: 350 | O75: 291 | P75: On-Time | Q75: 0
A76: FL074 | B76: 2022-10-24 | C76: Spirit | D76: Seattle | E76: SEA | F76: Orlando | G76: MCO | H76: 23:15 | I76: 01:20 | J76: 125 | K76: 1431 | M76: Business | N76: 187 | O76: 179 | P76: On-Time | Q76: 0
A77: FL075 | B77: 2022-01-06 | C77: JetBlue | D77: Las Vegas | E77: LAS | F77: San Diego | G77: SAN | H77: 18:45 | I77: 21:31 | J77: 166 | K77: 2129 | L77: 683.21 | M77: Business | N77: 185 | O77: 146 | P77: On-Time | Q77: 0
A78: FL076 | B78: 2023-10-22 | C78: Southwest | D78: Denver | E78: DEN | F78: San Diego | G78: SAN | H78: 12:15 | I78: 17:15 | J78: 300 | K78: 478 | L78: 436.36 | M78: Business | N78: 280 | O78: 257 | P78: On-Time | Q78: 0
A79: FL077 | B79: 2022-11-08 | C79: Frontier | D79: Los Angeles | E79: LAX | F79: Miami | G79: MIA | H79: 16:30 | I79: 18:51 | J79: 141 | K79: 2103 | L79: 191.68 | M79: Business | N79: 103 | P79: On-Time
A80: FL078 | B80: 2022-11-13 | C80: United | D80: Newark | E80: EWR | F80: Boston | G80: BOS | H80: 10:45 | I80: 17:47 | J80: 422 | K80: 628 | L80: 1033.98 | M80: First Class | N80: 319 | O80: 244 | P80: CANCELLED | Q80: 0
A81: FL079 | B81: 2024-09-26 | C81: Delta | D81: San Diego | E81: SAN | F81: Chicago | G81: ORD | H81: 07:30 | I81: 10:56 | J81: 206 | K81: 670 | L81: 566.05 | M81: Economy | N81: 294 | P81: Delayed | Q81: 40
A82: FL080 | B82: 2024-06-27 | C82: American | D82: Las Vegas | E82: LAS | F82: New York | G82: JFK | H82: 01:30 | I82: 03:28 | J82: 118 | K82: 1501 | L82: 481.48 | M82: Business | N82: 137 | O82: 81 | P82: On-Time | Q82: 0
A83: FL081 | B83: 2023-01-04 | C83: American | D83: Miami | E83: MIA | F83: Chicago | G83: ORD | H83: 19:45 | I83: 02:32 | J83: 407 | K83: 1286 | L83: 637.39 | M83: First Class | N83: 136 | O83: 79 | P83: On-Time | Q83: 0
A84: FL082 | B84: 2023-06-05 | C84: Frontier | D84: Boston | E84: BOS | F84: New York | G84: JFK | H84: 14:30 | I84: 21:46 | J84: 436 | K84: 2538 | L84: 256.93 | M84: Business | N84: 341 | O84: 226 | P84: Cancelled | Q84: 0
A85: FL083 | B85: 2023-09-05 | C85: spirit | D85: Boston | E85: BOS | F85: Newark | G85: EWR | H85: 09:15 | I85: 14:01 | J85: 286 | K85: 2279 | L85: 199.45 | N85: 246 | O85: 141 | P85: On-Time | Q85: 0
A86: FL084 | B86: 2023-08-28 | C86: Delta | D86: Minneapolis | E86: MSP | F86: Boston | G86: BOS | H86: 00:00 | I86: 06:40 | J86: 400 | K86: 2334 | L86: 1012.78 | M86: Business | N86: 298 | O86: 254 | P86: On-Time | Q86: 0
A87: FL085 | B87: 2023-12-23 | C87: Southwest | D87: Seattle | E87: SEA | F87: Las Vegas | G87: LAS | H87: 21:15 | I87: 04:06 | J87: 411 | K87: 697 | M87: First Class | N87: 110 | O87: 69 | P87: Delayed | Q87: 23
A88: FL086 | B88: 2024-01-18 | C88: American | D88: Chicago | E88: ORD | F88: Phoenix | G88: PHX | H88: 10:45 | I88: 13:44 | J88: 179 | K88: 1122 | L88: 228.02 | M88: First Class | N88: 324 | O88: 237 | P88: On-Time | Q88: 0
A89: FL087 | B89: 2023-07-13 | C89: American | D89: Boston | E89: BOS | F89: Houston | G89: IAH | H89: 09:30 | I89: 11:58 | J89: 148 | K89: 2218 | L89: 1158.44 | M89: Economy | N89: 293 | O89: 107 | P89: Delayed | Q89: 116
A90: FL088 | B90: 2024-01-20 | C90: United | D90: Minneapolis | E90: MSP | F90: New York | G90: JFK | H90: 08:00 | I90: 13:22 | J90: 322 | K90: 1809 | L90: 833.57 | M90: First Class | N90: 167 | O90: 124 | P90: On-Time | Q90: 0
A91: FL089 | B91: 2024-01-31 | C91: United | D91: Denver | E91: DEN | F91: Houston | G91: IAH | H91: 00:30 | I91: 07:12 | J91: 402 | K91: 1206 | L91: 805.37 | M91: First Class | N91: 310 | O91: 287 | P91: Delayed | Q91: 92
A92: FL090 | B92: 2024-04-16 | C92: United | D92: Dallas | E92: DFW | F92: Los Angeles | G92: LAX | H92: 01:30 | I92: 07:12 | J92: 342 | K92: 775 | L92: 188.86 | M92: First Class | N92: 134 | O92: 99 | P92: On-Time | Q92: 0
A93: FL091 | B93: 2024-05-08 | C93: american | D93: Detroit | E93: DTW | F93: Atlanta | G93: ATL | H93: 15:45 | I93: 19:38 | J93: 233 | K93: 434 | L93: 853.11 | M93: Economy | N93: 213 | P93: Cancelled | Q93: 0
A94: FL092 | B94: 2024-01-13 | C94: United | D94: San Francisco | E94: SFO | F94: Chicago | G94: MDW | H94: 20:30 | I94: 22:31 | J94: 121 | K94: 1930 | L94: 388.99 | M94: Economy | N94: 342 | O94: 282 | P94: On-Time | Q94: 0
A95: FL093 | B95: 2023-03-11 | C95: Delta | D95: Los Angeles | E95: LAX | F95: San Francisco | G95: SFO | H95: 07:15 | I95: 13:34 | J95: 379 | K95: 1140 | L95: 156.84 | M95: First Class | N95: 153 | O95: 125 | P95: On-Time | Q95: 0
A96: FL094 | B96: 2023-04-23 | C96: Alaska | D96: Dallas | E96: DFW | F96: New York | G96: JFK | H96: 08:15 | I96: 10:51 | J96: 156 | K96: 2512 | L96: 360.73 | M96: Economy | N96: 128 | O96: 53 | P96: On-Time | Q96: 0
A97: FL095 | B97: 2024-01-04 | C97: Southwest | D97: Chicago | E97: MDW | F97: Phoenix | G97: PHX | H97: 00:15 | I97: 04:00 | J97: 225 | K97: 514 | L97: 221.97 | M97: Business | N97: 234 | O97: 79 | P97: Delayed | Q97: 136
A98: FL096 | B98: 2024-07-07 | C98: Alaska | D98: Houston | E98: IAH | F98: San Diego | G98: SAN | H98: 03:45 | I98: 09:32 | J98: 347 | K98: 1207 | L98: 1138.87 | M98: Economy | N98: 286 | O98: 250 | P98: DELAYED | Q98: 148
A99: FL097 | B99: 2023-09-10 | C99: Frontier | D99: New York | E99: JFK | F99: Chicago | G99: ORD | H99: 15:45 | I99: 20:53 | J99: 308 | K99: 742 | L99: 629.1 | M99: Business | N99: 118 | O99: 60 | P99: On-Time | Q99: 0
A100: FL098 | B100: 2022-10-31 | C100: United | D100: Dallas | E100: DFW | F100: Las Vegas | G100: LAS | H100: 19:30 | I100: 00:15 | J100: 285 | K100: 2746 | L100: 674.22 | M100: Business | N100: 229 | O100: 204 | P100: On-Time | Q100: 0
A101: FL099 | B101: 2022-08-23 | C101: Southwest | D101: Detroit | E101: DTW | F101: Newark | G101: EWR | H101: 07:45 | I101: 12:08 | J101: 263 | K101: 2157 | L101: 526.58 | M101: First Class | N101: 124 | O101: 90 | P101: On-Time | Q101: 0
A102: FL100 | B102: 2023-06-07 | C102: Alaska | D102: Dallas | E102: DFW | F102: Houston | G102: IAH | H102: 02:00 | I102: 04:13 | J102: 133 | K102: 681 | L102: 563.7 | M102: First Class | N102: 289 | O102: 145 | P102: Delayed | Q102: 157
A103: FL101 | B103: 2022-05-03 | C103: Alaska | D103: Atlanta | E103: ATL | F103: Charlotte | G103: CLT | H103: 11:45 | I103: 19:24 | J103: 459 | K103: 510 | L103: 1164.61 | M103: First Class | N103: 179 | O103: 140 | P103: On-Time | Q103: 0
A104: FL102 | B104: 2024-11-05 | C104: Southwest | D104: Dallas | E104: DFW | F104: Houston | G104: IAH | H104: 07:00 | I104: 11:29 | J104: 269 | K104: 2578 | L104: 491.67 | M104: Business | N104: 246 | P104: Delayed | Q104: 158
...

Sheet ✈ Flights (2)
A1: Flight Id | B1: Flight Date | C1: Airline | D1: Origin City | E1: Origin Code | F1: Destination City | G1: Routes | H1: Destination Code | I1: Departure Time | J1: Arrival Time | K1: Flight Duration Min | L1: Distance Miles | M1: Ticket Price | N1: Class | O1: Seats Available | P1: Passengers Boarded | Q1: Occupancy Rate. | R1: Status | S1: Year-MONTH | T1: Delay Minutes
A2: FL001 | B2: 44790 | C2: Delta | D2: Boston | E2: BOS | F2: Denver | G2: =D2&" → "&F2 -> Boston → Denver | H2: DEN | I2: 07:15 | J2: 15:02 | K2: 467 | L2: 719 | M2: 837.9 | N2: First Class | O2: 122 | P2: 104 | Q2: =P2/O2*100 -> 85.245902 | R2: On-Time | S2: =TEXT(B2,"YYYY-MM") -> 2022-08 | T2: 0
A3: FL002 | B3: 44753 | C3: Southwest | D3: Denver | E3: DEN | F3: Orlando | G3: =D3&" → "&F3 -> Denver → Orlando | H3: MCO | I3: 19:00 | J3: 01:17 | K3: 377 | L3: 1114 | M3: 881.94 | N3: First Class | O3: 239 | P3: 157 | Q3: =P3/O3*100 -> 65.690377 | R3: On-Time | S3: =TEXT(B3,"YYYY-MM") -> 2022-07 | T3: 0
A4: FL003 | B4: 45131 | C4: Delta | D4: Miami | E4: MIA | F4: Charlotte | G4: =D4&" → "&F4 -> Miami → Charlotte | H4: CLT | I4: 10:30 | J4: 13:19 | K4: 169 | L4: 1181 | M4: 1152.08 | N4: Business | O4: 126 | P4: 61 | Q4: =P4/O4*100 -> 48.412698 | R4: On-Time | S4: =TEXT(B4,"YYYY-MM") -> 2023-07 | T4: 0
A5: FL004 | B5: 45297 | C5: Alaska | D5: San Diego | E5: SAN | F5: Boston | G5: =D5&" → "&F5 -> San Diego → Boston | H5: BOS | I5: 01:45 | J5: 07:49 | K5: 364 | L5: 811 | M5: 1169.89 | N5: Business | O5: 120 | P5: 120 | Q5: =P5/O5*100 -> 100 | R5: On-Time | S5: =TEXT(B5,"YYYY-MM") -> 2024-01 | T5: 0
A6: FL005 | B6: 45302 | C6: Southwest | D6: Chicago | E6: ORD | F6: Los Angeles | G6: =D6&" → "&F6 -> Chicago → Los Angeles | H6: LAX | I6: 21:15 | J6: 01:13 | K6: 238 | L6: 626 | M6: 1037.96 | N6: Economy | O6: 197 | P6: 121 | Q6: =P6/O6*100 -> 61.42132 | R6: On-Time | S6: =TEXT(B6,"YYYY-MM") -> 2024-01 | T6: 0
A7: FL006 | B7: 45309 | C7: American | D7: San Francisco | E7: SFO | F7: Minneapolis | G7: =D7&" → "&F7 -> San Francisco → Minneapolis | H7: MSP | I7: 06:30 | J7: 13:59 | K7: 449 | L7: 2954 | M7: 159.97 | N7: First Class | O7: 143 | P7: 118 | Q7: =P7/O7*100 -> 82.517483 | R7: Delayed | S7: =TEXT(B7,"YYYY-MM") -> 2024-01 | T7: 56 | Z7: Origin Code | AA7: Count of Flight Id
A8: FL007 | B8: 45508 | C8: Spirit | D8: Boston | E8: BOS | F8: Chicago | G8: =D8&" → "&F8 -> Boston → Chicago | H8: MDW | I8: 07:30 | J8: 09:28 | K8: 118 | L8: 1238 | M8: 1000.42 | N8: Business | O8: 202 | P8: 118 | Q8: =P8/O8*100 -> 58.415842 | R8: On-Time | S8: =TEXT(B8,"YYYY-MM") -> 2024-08 | T8: 0 | Z8: ATL | AA8: 33
A9: FL008 | B9: 45206 | C9: Southwest | D9: Newark | E9: EWR | F9: Minneapolis | G9: =D9&" → "&F9 -> Newark → Minneapolis | H9: MSP | I9: 20:45 | J9: 23:28 | K9: 163 | L9: 1384 | M9: 236.39 | N9: First Class | O9: 243 | P9: 187 | Q9: =P9/O9*100 -> 76.954733 | R9: On-Time | S9: =TEXT(B9,"YYYY-MM") -> 2023-10 | T9: 0 | Z9: LAX | AA9: 32
A10: FL009 | B10: 45439 | C10: Spirit | D10: San Francisco | E10: SFO | F10: Denver | G10: =D10&" → "&F10 -> San Francisco → Denver | H10: DEN | I10: 04:45 | J10: 07:01 | K10: 136 | L10: 492 | M10: 1044.44 | N10: Economy | O10: 260 | P10: 90 | Q10: =P10/O10*100 -> 34.615385 | R10: Delayed | S10: =TEXT(B10,"YYYY-MM") -> 2024-05 | T10: 123 | Z10: SAN | AA10: 30
A11: FL010 | B11: 44692 | C11: Spirit | D11: Minneapolis | E11: MSP | F11: Newark | G11: =D11&" → "&F11 -> Minneapolis → Newark | H11: EWR | I11: 16:30 | J11: 22:43 | K11: 373 | L11: 347 | M11: 587.19 | N11: Economy | O11: 274 | P11: 187 | Q11: =P11/O11*100 -> 68.248175 | R11: Delayed | S11: =TEXT(B11,"YYYY-MM") -> 2022-05 | T11: 179 | Z11: SFO | AA11: 28
A12: FL011 | B12: 45258 | C12: United | D12: Las Vegas | E12: LAS | F12: Charlotte | G12: =D12&" → "&F12 -> Las Vegas → Charlotte | H12: CLT | I12: 05:45 | J12: 07:16 | K12: 91 | L12: 1378 | M12: 587.19 | N12: Economy | O12: 229 | P12: 77 | Q12: =P12/O12*100 -> 33.624454 | R12: Delayed | S12: =TEXT(B12,"YYYY-MM") -> 2023-11 | T12: 91 | Z12: MSP | AA12: 27
A13: FL012 | B13: 45601 | C13: Southwest | D13: Dallas | E13: DFW | F13: Minneapolis | G13: =D13&" → "&F13 -> Dallas → Minneapolis | H13: MSP | I13: 05:00 | J13: 11:36 | K13: 396 | L13: 1627 | M13: 494.955 | N13: Economy | O13: 337 | P13: 235 | Q13: =P13/O13*100 -> 69.732938 | R13: Delayed | S13: =TEXT(B13,"YYYY-MM") -> 2024-11 | T13: 93 | Z13: CLT | AA13: 27
A14: FL013 | B14: 45052 | C14: Delta | D14: Denver | E14: DEN | F14: San Diego | G14: =D14&" → "&F14 -> Denver → San Diego | H14: SAN | I14: 02:00 | J14: 09:44 | K14: 464 | L14: 2290 | M14: 587.19 | N14: First Class | O14: 296 | P14: 82 | Q14: =P14/O14*100 -> 27.702703 | R14: On-Time | S14: =TEXT(B14,"YYYY-MM") -> 2023-05 | T14: 0 | Z14: JFK | AA14: 26
A15: FL014 | B15: 45535 | C15: American | D15: Boston | E15: BOS | F15: Orlando | G15: =D15&" → "&F15 -> Boston → Orlando | H15: MCO | I15: 19:45 | J15: 23:03 | K15: 198 | L15: 2508 | M15: 677.705 | N15: First Class | O15: 151 | P15: 141 | Q15: =P15/O15*100 -> 93.377483 | R15: On-Time | S15: =TEXT(B15,"YYYY-MM") -> 2024-08 | T15: 0 | Z15: DTW | AA15: 26
A16: FL015 | B16: 45326 | C16: Frontier | D16: Houston | E16: IAH | F16: Charlotte | G16: =D16&" → "&F16 -> Houston → Charlotte | H16: CLT | I16: 03:15 | J16: 06:40 | K16: 205 | L16: 562 | M16: 579.745 | N16: First Class | O16: 241 | P16: 108 | Q16: =P16/O16*100 -> 44.813278 | R16: On-Time | S16: =TEXT(B16,"YYYY-MM") -> 2024-02 | T16: 0 | Z16: BOS | AA16: 26
A17: FL016 | B17: 44576 | C17: United | D17: Los Angeles | E17: LAX | F17: Boston | G17: =D17&" → "&F17 -> Los Angeles → Boston | H17: BOS | I17: 02:00 | J17: 06:19 | K17: 259 | L17: 590 | M17: 498.48 | N17: Business | O17: 271 | P17: 174 | Q17: =P17/O17*100 -> 64.206642 | R17: On-Time | S17: =TEXT(B17,"YYYY-MM") -> 2022-01 | T17: 0 | Z17: PHX | AA17: 25
A18: FL017 | B18: 44832 | C18: Frontier | D18: Denver | E18: DEN | F18: Houston | G18: =D18&" → "&F18 -> Denver → Houston | H18: IAH | I18: 13:15 | J18: 15:33 | K18: 138 | L18: 697 | M18: 527.085 | N18: Business | O18: 208 | P18: 155 | Q18: =P18/O18*100 -> 74.519231 | R18: On-Time | S18: =TEXT(B18,"YYYY-MM") -> 2022-09 | T18: 0 | Z18: MDW | AA18: 25
A19: FL018 | B19: 44672 | C19: United | D19: Los Angeles | E19: LAX | F19: Detroit | G19: =D19&" → "&F19 -> Los Angeles → Detroit | H19: DTW | I19: 23:30 | J19: 01:55 | K19: 145 | L19: 1318 | M19: 627.39 | N19: First Class | O19: 214 | P19: 85 | Q19: =P19/O19*100 -> 39.719626 | R19: On-Time | S19: =TEXT(B19,"YYYY-MM") -> 2022-04 | T19: 0 | Z19: ORD | AA19: 24
... A28: FL027 | B28: 45102 | C28: Frontier | D28: Boston | E28: BOS | F28: Los Angeles | G28: =D28&" → "&F28 -> Boston → Los Angeles | H28: LAX | I28: 02:45 | J28: 06:36 | K28: 231 | L28: 480 | M28: 498.48 | N28: Economy | O28: 263 | P28: 117 | Q28: =P28/O28*100 -> 44.486692 | R28: On-Time | S28: =TEXT(B28,"YYYY-MM") -> 2023-06 | T28: 0 | Z28: Grand Total | AA28: 500
A29: FL028 | B29: 45466 | C29: Spirit | D29: Orlando | E29: MCO | F29: New York | G29: =D29&" → "&F29 -> Orlando → New York | H29: JFK | I29: 03:00 | J29: 10:23 | K29: 443 | L29: 910 | M29: 587.19 | N29: Business | O29: 249 | P29: 142 | Q29: =P29/O29*100 -> 57.028112 | R29: On-Time | S29: =TEXT(B29,"YYYY-MM") -> 2024-06 | T29: 0
A30: FL029 | B30: 44823 | C30: Delta | D30: Las Vegas | E30: LAS | F30: Minneapolis | G30: =D30&" → "&F30 -> Las Vegas → Minneapolis | H30: MSP | I30: 01:30 | J30: 04:47 | K30: 197 | L30: 1322 | M30: 527.085 | N30: Business | O30: 299 | P30: 193 | Q30: =P30/O30*100 -> 64.548495 | R30: Delayed | S30: =TEXT(B30,"YYYY-MM") -> 2022-09 | T30: 119
A31: FL030 | B31: 44878 | C31: Southwest | D31: Miami | E31: MIA | F31: Seattle | G31: =D31&" → "&F31 -> Miami → Seattle | H31: SEA | I31: 13:00 | J31: 16:01 | K31: 181 | L31: 1660 | M31: 956.27 | N31: Business | O31: 305 | P31: 177 | Q31: =P31/O31*100 -> 58.032787 | R31: On-Time | S31: =TEXT(B31,"YYYY-MM") -> 2022-11 | T31: 0
A32: FL031 | B32: 44783 | C32: Spirit | D32: Los Angeles | E32: LAX | F32: Houston | G32: =D32&" → "&F32 -> Los Angeles → Houston | H32: IAH | I32: 07:15 | J32: 12:40 | K32: 325 | L32: 1732 | M32: 587.19 | N32: Economy | O32: 157 | P32: 53 | Q32: =P32/O32*100 -> 33.757962 | R32: Delayed | S32: =TEXT(B32,"YYYY-MM") -> 2022-08 | T32: 117
A33: FL032 | B33: 45234 | C33: Jetblue | D33: Chicago | E33: ORD | F33: Las Vegas | G33: =D33&" → "&F33 -> Chicago → Las Vegas | H33: LAS | I33: 11:45 | J33: 19:02 | K33: 437 | L33: 2496 | M33: 450.89 | N33: Economy | O33: 129 | P33: 83 | Q33: =P33/O33*100 -> 64.341085 | R33: On-Time | S33: =TEXT(B33,"YYYY-MM") -> 2023-11 | T33: 0
A34: FL033 | B34: 45105 | C34: Delta | D34: Atlanta | E34: ATL | F34: Charlotte | G34: =D34&" → "&F34 -> Atlanta → Charlotte | H34: CLT | I34: 11:30 | J34: 16:43 | K34: 313 | L34: 2783 | M34: 1182.34 | N34: Economy | O34: 198 | P34: 197 | Q34: =P34/O34*100 -> 99.494949 | R34: On-Time | S34: =TEXT(B34,"YYYY-MM") -> 2023-06 | T34: 0
A35: FL034 | B35: 44652 | C35: Spirit | D35: New York | E35: JFK | F35: Orlando | G35: =D35&" → "&F35 -> New York → Orlando | H35: MCO | I35: 17:15 | J35: 21:51 | K35: 276 | L35: 2066 | M35: 158.37 | N35: First Class | O35: 335 | P35: 219 | Q35: =P35/O35*100 -> 65.373134 | R35: On-Time | S35: =TEXT(B35,"YYYY-MM") -> 2022-04 | T35: 0
A36: FL035 | B36: 44817 | C36: Jetblue | D36: Houston | E36: IAH | F36: Las Vegas | G36: =D36&" → "&F36 -> Houston → Las Vegas | H36: LAS | I36: 21:45 | J36: 02:02 | K36: 257 | L36: 1948 | M36: 860.87 | N36: First Class | O36: 132 | P36: 74 | Q36: =P36/O36*100 -> 56.060606 | R36: On-Time | S36: =TEXT(B36,"YYYY-MM") -> 2022-09 | T36: 0
A37: FL036 | B37: 45338 | C37: American | D37: San Diego | E37: SAN | F37: Chicago | G37: =D37&" → "&F37 -> San Diego → Chicago | H37: MDW | I37: 09:45 | J37: 15:55 | K37: 370 | L37: 301 | M37: 420.34 | N37: Economy | O37: 210 | P37: 198 | Q37: =P37/O37*100 -> 94.285714 | R37: On-Time | S37: =TEXT(B37,"YYYY-MM") -> 2024-02 | T37: 0
A38: FL037 | B38: 45221 | C38: Frontier | D38: Charlotte | E38: CLT | F38: Newark | G38: =D38&" → "&F38 -> Charlotte → Newark | H38: EWR | I38: 21:15 | J38: 03:06 | K38: 351 | L38: 2238 | M38: 968.98 | N38: First Class | O38: 143 | P38: 134 | Q38: =P38/O38*100 -> 93.706294 | R38: On-Time | S38: =TEXT(B38,"YYYY-MM") -> 2023-10 | T38: 0
A39: FL038 | B39: 45617 | C39: Alaska | D39: Chicago | E39: ORD | F39: Boston | G39: =D39&" → "&F39 -> Chicago → Boston | H39: BOS | I39: 21:30 | J39: 00:55 | K39: 205 | L39: 1115 | M39: 245.04 | N39: Economy | O39: 162 | P39: 110 | Q39: =P39/O39*100 -> 67.901235 | R39: On-Time | S39: =TEXT(B39,"YYYY-MM") -> 2024-11 | T39: 0
A40: FL039 | B40: 44711 | C40: Frontier | D40: Detroit | E40: DTW | F40: San Diego | G40: =D40&" → "&F40 -> Detroit → San Diego | H40: SAN | I40: 06:45 | J40: 12:28 | K40: 343 | L40: 1936 | M40: 353.26 | N40: First Class | O40: 276 | P40: 51 | Q40: =P40/O40*100 -> 18.478261 | R40: Delayed | S40: =TEXT(B40,"YYYY-MM") -> 2022-05 | T40: 42
... A501: FL500 | B501: 45506 | C501: Spirit | D501: Chicago | E501: MDW | F501: Seattle | G501: =D501&" → "&F501 -> Chicago → Seattle | H501: SEA | I501: 16:30 | J501: 23:46 | K501: 436 | L501: 1036 | M501: 430.86 | N501: Economy | O501: 272 | P501: 52 | Q501: =P501/O501*100 -> 19.117647 | R501: Delayed | S501: =TEXT(B501,"YYYY-MM") -> 2024-08 | T501: 18

Sheet 🏢 Airports
A1: 🏢 AIRPORTS REFERENCE TABLE
A2: Airport Code | B2: Airport Name | C2: City | D2: Country | E2: Terminals | F2: Annual Capacity
A3: JFK | B3: John F. Kennedy International | C3: New York | D3: USA | E3: 8 | F3: 62000000
A4: LAX | B4: Los Angeles International | C4: Los Angeles | D4: USA | E4: 9 | F4: 88000000
A5: ORD | B5: O'Hare International | C5: Chicago | D5: USA | E5: 4 | F5: 54000000
A6: ATL | B6: Hartsfield-Jackson Atlanta | C6: Atlanta | D6: USA | E6: 2 | F6: 107000000
A7: DFW | B7: Dallas/Fort Worth International | C7: Dallas | D7: USA | E7: 5 | F7: 73000000
A8: MIA | B8: Miami International | C8: Miami | D8: USA | E8: 3 | F8: 45000000
A9: SEA | B9: Seattle-Tacoma International | C9: Seattle | D9: USA | E9: 3 | F9: 51000000
A10: DEN | B10: Denver International | C10: Denver | D10: USA | E10: 3 | F10: 69000000
A11: BOS | B11: Logan International | C11: Boston | D11: USA | E11: 4 | F11: 40000000
A12: LAS | B12: Harry Reid International | C12: Las Vegas | D12: USA | E12: 2 | F12: 51000000
A13: PHX | B13: Phoenix Sky Harbor | C13: Phoenix | D13: USA | E13: 3 | F13: 46000000
A14: SFO | B14: San Francisco International | C14: San Francisco | D14: USA | E14: 4 | F14: 57000000
... A22: SAN | B22: San Diego International | C22: San Diego | D22: USA | E22: 2 | F22: 25000000
S510: =VLOOKUP(B2,Flights!$A$2:$P$508,12,0)'

Sheet 💰 Revenue
A1: 💰 REVENUE & COSTS TABLE (Contains Dirty Data)
A2: Revenue Id | B2: Flight Id | C2: Airport Code | D2: Total Revenue | E2: Ancillary Revenue | F2: Fuel Cost | G2: Crew Cost | H2: Profit | I2: Payment Method
A3: REV001 | B3: FL001 | C3: BOS | D3: 87141.6 | E3: 1232.74 | F3: 8636.75 | G3: 7797.25 | H3: 71940.34 | I3: Cash
A4: REV002 | B4: FL002 | C4: DEN | D4: 138464.58 | E4: 5939.38 | F4: 13816.36 | G4: 2442.54 | H4: 128145.06 | I4: Credit Card
A5: REV003 | B5: FL003 | C5: MIA | D5: 70276.88 | E5: 926.61 | F5: 25794.85 | G5: 13621.57 | H5: 31787.07 | I5: Cash
A6: REV004 | B6: FL004 | C6: SAN | D6: 140386.8 | E6: 7628.67 | F6: 27332.9 | G6: 11204.98 | H6: 109477.59 | I6: Credit Card
A7: REV005 | B7: FL005 | C7: ORD | D7: 125593.16 | E7: 1147.9 | F7: 26164 | G7: 6887.46 | H7: 93689.6 | I7: Cash
A8: REV006 | B8: FL006 | C8: SFO | D8: 18876.46 | E8: 7220.01 | F8: 29347.88 | G8: 5293.36 | H8: -8544.77 | I8: Debit Card
A9: REV007 | B9: FL007 | C9: BOS | D9: 118049.56 | E9: 5453.58 | F9: 7650 | G9: 7894.77 | H9: 107958.37 | I9: Travel Points
A10: REV008 | B10: FL008 | C10: EWR | D10: 44204.93 | E10: 6270.19 | F10: 29227.75 | G10: 10678.53 | H10: 10568.84 | I10: Travel Points
A11: REV009 | B11: FL009 | C11: SFO | D11: 93999.6 | E11: 2430.02 | F11: 32325.6 | G11: 5604.74 | H11: 58499.28 | I11: Credit Card
A12: REV010 | B12: FL010 | C12: MSP | D12: 157439.04 | E12: 3370.99 | F12: 16642.92 | G12: 2780.76 | H12: 141386.35 | I12: Travel Points
A13: REV011 | B13: FL011 | C13: LAS | D13: 89975.27 | E13: 1834.47 | F13: 7428.95 | G13: 14732.49 | H13: 69648.3 | I13: Cash
A14: REV012 | B14: FL012 | C14: DFW | D14: 147401.4 | E14: 5077.26 | F14: 11245.48 | G14: 8396.74 | H14: 132836.44 | I14: Cash
... A63: REV061 | B63: FL061 | C63: DFW | D63: 142418.08 | E63: 7213.09 | F63: 30249.11 | G63: 9705.19 | H63: 109676.87 | I63: Travel Points
A64: REV062 | B64: FL062 | C64: CLT | D64: 0 | E64: 0 | G64: 11712.13 | H64: -31379.45 | I64: Travel Points
A65: REV063 | B65: FL063 | C65: BOS | D65: 27071.55 | E65: 2225.47 | F65: 8854.65 | G65: 4961.17 | H65: 15481.2 | I65: Cash
A66: REV064 | B66: FL064 | C66: DEN | D66: 29548.2 | E66: 6033.11 | F66: 35446.02 | G66: 6881.92 | H66: -6746.63 | I66: Cash
A67: REV065 | B67: FL065 | C67: ATL | D67: 20477.44 | E67: 1051.47 | F67: 25478.23 | G67: 2706.41 | H67: -6655.73 | I67: Debit Card
A68: REV066 | B68: FL066 | C68: ATL | D68: 199900.8 | E68: 1587.06 | F68: 37476.05 | G68: 7914.88 | H68: 156096.93 | I68: Debit Card
A69: REV067 | B69: FL067 | C69: PHX | D69: 163742.76 | E69: 3301.14 | F69: 21020.91 | G69: 4524.01 | H69: 141498.98 | I69: Travel Points
A70: REV068 | B70: FL068 | C70: EWR | D70: 308717.64 | E70: 7816.67 | F70: 12077.38 | G70: 3653.75 | H70: 300803.18 | I70: Credit Card
A71: REV069 | B71: FL069 | C71: SFO | D71: 183156.16 | E71: 2604.53 | F71: 8888.82 | G71: 8051.95 | H71: 168819.92 | I71: Debit Card
A72: REV070 | B72: FL070 | C72: CLT | D72: 365148.93 | E72: 1784.01 | F72: 17025.16 | G72: 13523.32 | H72: 336384.46 | I72: Cash
A73: REV071 | B73: FL071 | C73: LAX | D73: 65558.64 | E73: 6421.6 | F73: 27329.97 | G73: 9949.87 | H73: 34700.4 | I73: Cash
A74: REV072 | B74: FL072 | C74: EWR | D74: 65918.16 | E74: 4835.91 | F74: 24346.45 | G74: 4986.13 | H74: 41421.49 | I74: Debit Card
A75: REV073 | B75: FL073 | C75: ATL | D75: 158696.85 | E75: 6927.3 | F75: 22122.47 | G75: 14943.64 | H75: 128558.04 | I75: Debit Card
A76: REV074 | B76: FL074 | C76: SEA | D76: 169226.6 | E76: 6777.42 | F76: 14770.98 | G76: 11490.23 | H76: 149742.81 | I76: Cash
... A93: REV091 | B93: FL091 | C93: DTW | D93: 0 | E93: 0 | F93: 17825.15 | G93: 10426.24 | H93: -28251.39 | I93: Credit Card
A94: REV092 | B94: FL092 | C94: SFO | D94: 109695.18 | E94: 4705.69 | G94: 3799.28 | H94: 78526.45 | I94: Travel Points
A95: REV093 | B95: FL093 | C95: LAX | D95: 19605 | E95: 2289.75 | F95: 8974.52 | G95: 8220.42 | H95: 4699.81 | I95: Cash
A96: REV094 | B96: FL094 | C96: DFW | D96: 19118.69 | E96: 6148.8 | F96: 31631.01 | G96: 6166.03 | H96: -12529.55 | I96: Travel Points
A97: REV095 | B97: FL095 | C97: MDW | D97: 17535.63 | E97: 4276.74 | F97: 19802.52 | G97: 2707.98 | H97: -698.13 | I97: Travel Points
A98: REV096 | B98: FL096 | C98: IAH | D98: 284717.5 | E98: 3089.2 | F98: 22017.94 | G98: 8846.87 | H98: 256941.89 | I98: Credit Card
A99: REV097 | B99: FL097 | C99: JFK | D99: 37746 | E99: 4026.23 | F99: 23616.66 | G99: 12729.93 | H99: 5425.64 | I99: Travel Points
A100: REV098 | B100: FL098 | C100: DFW | D100: 137540.88 | E100: 3889.84 | F100: 17885.1 | G100: 10752.98 | H100: 112792.64 | I100: Credit Card
A101: REV099 | B101: FL099 | C101: DTW | D101: 47392.2 | E101: 1912.65 | F101: 35939.26 | G101: 3135.01 | H101: 10230.58 | I101: Debit Card
A102: REV100 | B102: FL100 | C102: DFW | D102: 81736.5 | E102: 7234.59 | F102: 15093.04 | G102: 14436.15 | H102: 59441.9 | I102: Credit Card
A103: REV101 | B103: FL101 | C103: ATL | D103: 163045.4 | E103: 1735.75 | F103: 8920.86 | G103: 3923.4 | H103: 151936.89 | I103: Cash
A104: REV102 | B104: FL102 | C104: DFW | D104: 52608.69 | E104: 7062.45 | F104: 23224.07 | G104: 10154.59 | H104: 26292.48 | I104: Travel Points
A105: REV103 | B105: FL103 | C105: JFK | D105: 18931.12 | E105: 3624.02 | F105: 28884.12 | G105: 14112.38 | H105: -20441.36 | I105: Debit Card
A106: REV104 | B106: FL104 | C106: ORD | D106: 61419.4 | E106: 3100.25 | F106: 20535.1 | G106: 10380.9 | H106: 33603.65 | I106: Travel Points
... A163: REV161 | B163: FL161 | C163: DFW | D163: 76785.57 | E163: 2167.68 | F163: 34988.53 | G163: 3850.67 | H163: 40114.05 | I163: Cash
A164: REV162 | B164: FL162 | C164: EWR | D164: 154221.2 | E164: 2805.71 | G164: 14754.42 | H164: 129928.05 | I164: Debit Card
A165: REV163 | B165: FL163 | C165: SEA | D165: 130233.36 | E165: 5681.14 | F165: 32441.04 | G165: 3010.56 | H165: 100462.9 | I165: Debit Card
A166: REV164 | B166: FL164 | C166: MCO | D166: 0 | E166: 0 | F166: 31506.69 | G166: 2552.72 | H166: -34059.41 | I166: Credit Card
A167: REV165 | B167: FL165 | C167: LAX | D167: 84727.76 | E167: 745.95 | F167: 28092.61 | G167: 9711.29 | H167: 47669.81 | I167: Debit Card
A168: REV166 | B168: FL166 | C168: DFW | D168: 108757.51 | E168: 1391.92 | F168: 13855.44 | G168: 2861.22 | H168: 93432.77 | I168: Credit Card
A169: REV167 | B169: FL167 | C169: PHX | D169: 200969.46 | E169: 6159.13 | F169: 32382.98 | G169: 13961.27 | H169: 160784.34 | I169: Cash
A170: REV168 | B170: FL168 | C170: PHX | D170: 169912.05 | E170: 4907.02 | F170: 12000.85 | G170: 10717.81 | H170: 152100.41 | I170: Credit Card
A171: REV169 | B171: FL169 | C171: MIA | D171: 129557.9 | E171: 1180.84 | F171: 34605.15 | G171: 14243.98 | H171: 81889.61 | I171: Travel Points
A172: REV170 | B172: FL170 | C172: CLT | D172: 64647.26 | E172: 3141.52 | F172: 34929.83 | G172: 12150.43 | H172: 20708.52 | I172: Cash
A173: REV171 | B173: FL171 | C173: MIA | D173: 106922.24 | E173: 4286.82 | F173: 7391.8 | G173: 12654.62 | H173: 91162.64 | I173: Credit Card
A174: REV172 | B174: FL172 | C174: ORD | D174: 40573.5 | E174: 4466.29 | F174: 30053.41 | G174: 14535.43 | H174: 450.95 | I174: Cash
A175: REV173 | B175: FL173 | C175: PHX | D175: 31375.5 | E175: 7262.45 | G175: 14656.54 | H175: 181.98 | I175: Credit Card
A176: REV174 | B176: FL174 | C176: IAH | D176: 32940.55 | E176: 7431.74 | F176: 37216.7 | G176: 13066.86 | H176: -9911.27 | I176: Debit Card
A177: REV175 | B177: FL175 | C177: DTW | D177: 76620.18 | E177: 3248.47 | F177: 25628.32 | G177: 7715.66 | H177: 46524.67 | I177: Credit Card
A178: REV176 | B178: FL176 | C178: ORD | D178: 21755.82 | E178: 1856.36 | F178: 17418.78 | G178: 6935 | H178: -741.6 | I178: Cash
A179: REV177 | B179: FL177 | C179: ATL | D179: 48052.02 | E179: 4356.88 | F179: 19265.23 | G179: 11898.32 | H179: 21245.35 | I179: Travel Points
A180: REV178 | B180: FL178 | C180: MCO | D180: 54963.3 | E180: 1427.12 | F180: 8861.07 | G180: 3766.86 | H180: 43762.49 | I180: Travel Points
A181: REV179 | B181: FL179 | C181: SFO | D181: 7741.18 | E181: 5785.48 | F181: 24499.62 | G181: 2527.91 | H181: -13500.87 | I181: Travel Points
A182: REV180 | B182: FL180 | C182: MSP | D182: 0 | E182: 0 | F182: 22279.95 | G182: 7002.15 | H182: -29282.1 | I182: Debit Card
A183: REV181 | B183: FL181 | C183: DEN | D183: 0 | E183: 5002.92 | F183: 15920.24 | G183: 14690.33 | H183: 67080.69 | I183: Debit Card
A184: REV182 | B184: FL182 | C184: BOS | D184: 58421.96 | E184: 2194.05 | F184: 19254.88 | G184: 14804.51 | H184: 26556.62 | I184: Debit Card
A185: REV183 | B185: FL183 | C185: SAN | D185: 92806.66 | E185: 1915.89 | F185: 7436.32 | G185: 12933.76 | H185: 74352.47 | I185: Debit Card
A186: REV184 | B186: FL184 | C186: DEN | D186: 112509.46 | E186: 7543.12 | F186: 17860.45 | G186: 2166.22 | H186: 100025.91 | I186: Debit Card
A187: REV185 | B187: FL185 | C187: MCO | D187: 0 | E187: 0 | F187: 28523.34 | G187: 7152.81 | H187: -35676.15 | I187: Credit Card
... A281: REV279 | B281: FL279 | C281: DTW | D281: 30981.75 | E281: 5000.62 | F281: 39832.26 | G281: 5678.57 | H281: -9528.46 | I281: Cash
A282: REV280 | B282: FL280 | C282: LAX | D282: 172474.72 | E282: 3637.48 | G282: 3897.26 | H282: 152916.6 | I282: Travel Points
A283: REV281 | B283: FL281 | C283: MIA | D283: 210034.14 | E283: 7820.96 | F283: 13242 | G283: 7862.7 | H283: 196750.4 | I283: Cash
A284: REV282 | B284: FL282 | C284: SFO | D284: 29241.42 | E284: 3272.28 | F284: 28949.35 | G284: 7956.13 | H284: -4391.78 | I284: Credit Card
A285: REV283 | B285: FL283 | C285: ATL | D285: 140062.8 | E285: 4016.61 | F285: 35500.52 | G285: 14667.19 | H285: 93911.7 | I285: Debit Card
A286: REV284 | B286: FL284 | C286: MCO | D286: 13811.26 | E286: 5651.39 | F286: 29966.76 | G286: 11209.89 | H286: -21714 | I286: Travel Points
A287: REV285 | B287: FL285 | C287: ATL | D287: 23239.65 | E287: 1047.92 | F287: 24495 | G287: 2677.46 | H287: -2884.89 | I287: Cash
A288: REV286 | B288: FL286 | C288: PHX | D288: 116616.1 | E288: 4031.99 | F288: 17400.56 | G288: 9882.87 | H288: 93364.66 | I288: Credit Card
A289: REV287 | B289: FL287 | C289: ATL | D289: 76190.4 | E289: 540.21 | F289: 22658.97 | G289: 6952.19 | H289: 47119.45 | I289: Debit Card
A290: REV288 | B290: FL288 | C290: MCO | D290: 36807.15 | E290: 5534.47 | F290: 9628.34 | G290: 13598.94 | H290: 19114.34 | I290: Credit Card
A291: REV289 | B291: FL289 | C291: SAN | D291: 25284.27 | E291: 4853.65 | F291: 14110.21 | G291: 8548.71 | H291: 7479 | I291: Travel Points
A292: REV290 | B292: FL290 | C292: LAS | D292: 54983.28 | E292: 7084.23 | F292: 9617.18 | G292: 6125.13 | H292: 46325.2 | I292: Debit Card
A293: REV291 | B293: FL291 | C293: SEA | D293: 72589.14 | E293: 1563.47 | F293: 9089.47 | G293: 2574.11 | H293: 62489.03 | I293: Cash
A294: REV292 | B294: FL292 | C294: LAS | D294: 17087.84 | E294: 4244.08 | F294: 39068 | G294: 5653.01 | H294: -23389.09 | I294: Travel Points
... A325: REV323 | B325: FL323 | C325: MDW | D325: 46210.15 | E325: 2680.27 | F325: 20307.44 | G325: 13793.7 | H325: 14789.28 | I325: Debit Card
A326: REV324 | B326: FL324 | C326: LAX | D326: 118192.5 | E326: 2752.95 | G326: 10896.08 | H326: 70602.85 | I326: Travel Points
A327: REV325 | B327: FL325 | C327: LAX | D327: 107528.85 | E327: 6811.53 | F327: 23308.22 | G327: 5841.26 | H327: 85190.9 | I327: Credit Card
A328: REV326 | B328: FL326 | C328: JFK | D328: 53367.32 | E328: 4632.46 | F328: 37105.57 | G328: 8674.39 | H328: 12219.82 | I328: Debit Card
A329: REV327 | B329: FL327 | C329: ATL | D329: 121158.72 | E329: 3597.65 | F329: 21262.98 | G329: 11364.03 | H329: 92129.36 | I329: Travel Points
A330: REV328 | B330: FL328 | C330: DTW | D330: 92374.11 | E330: 3165.93 | F330: 25494.88 | G330: 11992.41 | H330: 58052.75 | I330: Credit Card
A331: REV329 | B331: FL329 | C331: MDW | D331: 27174.51 | E331: 1354.52 | F331: 28155.24 | G331: 4334.18 | H331: -3960.39 | I331: Cash
A332: REV330 | B332: FL330 | C332: DTW | D332: 59893.38 | E332: 6821.82 | F332: 6584.06 | G332: 7411.27 | H332: 52719.87 | I332: Travel Points
A333: REV331 | B333: FL331 | C333: MCO | D333: 107511.66 | E333: 2854.6 | F333: 30343.31 | G333: 11845.61 | H333: 68177.34 | I333: Debit Card
A334: REV332 | B334: FL332 | C334: ATL | D334: 211256.94 | E334: 5178.58 | F334: 14277.6 | G334: 14567.36 | H334: 187590.56 | I334: Cash
A335: REV333 | B335: FL333 | C335: IAH | D335: 121279.28 | E335: 2083.01 | F335: 7737.72 | G335: 14768.42 | H335: 100856.15 | I335: Travel Points
A336: REV334 | B336: FL334 | C336: LAX | D336: 37592.54 | E336: 7037.12 | F336: 8721.57 | G336: 8946.89 | H336: 26961.2 | I336: Credit Card
A337: REV335 | B337: FL335 | C337: IAH | D337: 34432.65 | E337: 3462 | F337: 5465.66 | G337: 10525.41 | H337: 21903.58 | I337: Debit Card
A338: REV336 | B338: FL336 | C338: SAN | D338: 103139.29 | E338: 5688.55 | F338: 35407.32 | G338: 14555.45 | H338: 58865.07 | I338: Debit Card
... A372: REV370 | B372: FL370 | C372: IAH | D372: 55942.64 | E372: 5811.23 | F372: 31668.76 | G372: 8479.08 | H372: 21606.03 | I372: Credit Card
A373: REV371 | B373: FL371 | C373: MDW | D373: 177709.44 | E373: 1657.22 | G373: 12649.09 | H373: 148986.78 | I373: Credit Card
A374: REV372 | B374: FL372 | C374: BOS | D374: 71422.32 | E374: 6864.46 | F374: 20368.8 | G374: 7404.75 | H374: 50513.23 | I374: Credit Card
A375: REV373 | B375: FL373 | C375: SEA | D375: 60249 | E375: 2339.87 | F375: 33320.08 | G375: 6437.16 | H375: 22831.63 | I375: Cash
A376: REV374 | B376: FL374 | C376: DFW | D376: 20231.64 | E376: 1139.25 | F376: 18035.27 | G376: 11812.99 | H376: -8477.37 | I376: Travel Points
...

Sheet 💰 Revenue (2)
A1: Revenue Id | B1: Flight Id | C1: Airport Code | D1: Airline | E1: Total Revenue | F1: Revenue Per Mile | G1: Ancillary Revenue | H1: Crew Cost | I1: Fuel Cost2 | J1: Profit | K1: Payment Method | L1: Ticket price | M1: Passenger Boarded | N1: Class | O1: Distance Mile
A2: REV001 | B2: FL001 | C2: BOS | D2: =VLOOKUP(B2,'✈ Flights (2)'!$A$2:$P$502,3,FALSE) -> Delta | E2: 87141.6 | F2: =E2/O2 -> 121.19833 | G2: 1232.74 | H2: 7797.25 | I2: 8636.75 | J2: 71940.34 | K2: Cash | L2: =VLOOKUP(B2,'✈ Flights (2)'!$A$2:$R$501,13,FALSE) -> 837.9 | M2: =VLOOKUP(B2,'✈ Flights (2)'!$A$2:$R$501,16,FALSE) -> 104 | N2: =VLOOKUP(B2,'✈ Flights (2)'!$A$2:$R$501,14,FALSE) -> First Class | O2: =VLOOKUP(B2,'✈ Flights (2)'!$A$2:$P$502,12,FALSE) -> 719
A3: REV002 | B3: FL002 | C3: DEN | D3: =VLOOKUP(B3,'✈ Flights (2)'!$A$2:$P$502,3,FALSE) -> Southwest | E3: 138464.58 | F3: =E3/O3 -> 124.29496 | G3: 5939.38 | H3: 2442.54 | I3: 13816.36 | J3: 128145.06 | K3: Credit Card | L3: =VLOOKUP(B3,'✈ Flights (2)'!$A$2:$R$501,13,FALSE) -> 881.94 | M3: =VLOOKUP(B3,'✈ Flights (2)'!$A$2:$R$501,16,FALSE) -> 157 | N3: =VLOOKUP(B3,'✈ Flights (2)'!$A$2:$R$501,14,FALSE) -> First Class | O3: =VLOOKUP(B3,'✈ Flights (2)'!$A$2:$P$502,12,FALSE) -> 1114
A4: REV003 | B4: FL003 | C4: MIA | D4: =VLOOKUP(B4,'✈ Flights (2)'!$A$2:$P$502,3,FALSE) -> Delta | E4: 70276.88 | F4: =E4/O4 -> 59.506249 | G4: 926.61 | H4: 13621.57 | I4: 25794.85 | J4: 31787.07 | K4: Cash | L4: =VLOOKUP(B4,'✈ Flights (2)'!$A$2:$R$501,13,FALSE) -> 1152.08 | M4: =VLOOKUP(B4,'✈ Flights (2)'!$A$2:$R$501,16,FALSE) -> 61 | N4: =VLOOKUP(B4,'✈ Flights (2)'!$A$2:$R$501,14,FALSE) -> Business | O4: =VLOOKUP(B4,'✈ Flights (2)'!$A$2:$P$502,12,FALSE) -> 1181
A5: REV004 | B5: FL004 | C5: SAN | D5: =VLOOKUP(B5,'✈ Flights (2)'!$A$2:$P$502,3,FALSE) -> Alaska | E5: 140386.8 | F5: =E5/O5 -> 173.10333 | G5: 7628.67 | H5: 11204.98 | I5: 27332.9 | J5: 109477.59 | K5: Credit Card | L5: =VLOOKUP(B5,'✈ Flights (2)'!$A$2:$R$501,13,FALSE) -> 1169.89 | M5: =VLOOKUP(B5,'✈ Flights (2)'!$A$2:$R$501,16,FALSE) -> 120 | N5: =VLOOKUP(B5,'✈ Flights (2)'!$A$2:$R$501,14,FALSE) -> Business | O5: =VLOOKUP(B5,'✈ Flights (2)'!$A$2:$P$502,12,FALSE) -> 811
A6: REV005 | B6: FL005 | C6: ORD | D6: =VLOOKUP(B6,'✈ Flights (2)'!$A$2:$P$502,3,FALSE) -> Southwest | E6: 125593.16 | F6: =E6/O6 -> 200.62805 | G6: 1147.9 | H6: 6887.46 | I6: 26164 | J6: 93689.6 | K6: Cash | L6: =VLOOKUP(B6,'✈ Flights (2)'!$A$2:$R$501,13,FALSE) -> 1037.96 | M6: =VLOOKUP(B6,'✈ Flights (2)'!$A$2:$R$501,16,FALSE) -> 121 | N6: =VLOOKUP(B6,'✈ Flights (2)'!$A$2:$R$501,14,FALSE) -> Economy | O6: =VLOOKUP(B6,'✈ Flights (2)'!$A$2:$P$502,12,FALSE) -> 626
A7: REV006 | B7: FL006 | C7: SFO | D7: =VLOOKUP(B7,'✈ Flights (2)'!$A$2:$P$502,3,FALSE) -> American | E7: 18876.46 | F7: =E7/O7 -> 6.3901354 | G7: 7220.01 | H7: 5293.36 | I7: 29347.88 | J7: -8544.77 | K7: Debit Card | L7: =VLOOKUP(B7,'✈ Flights (2)'!$A$2:$R$501,13,FALSE) -> 159.97 | M7: =VLOOKUP(B7,'✈ Flights (2)'!$A$2:$R$501,16,FALSE) -> 118 | N7: =VLOOKUP(B7,'✈ Flights (2)'!$A$2:$R$501,14,FALSE) -> First Class | O7: =VLOOKUP(B7,'✈ Flights (2)'!$A$2:$P$502,12,FALSE) -> 2954
A8: REV007 | B8: FL007 | C8: BOS | D8: =VLOOKUP(B8,'✈ Flights (2)'!$A$2:$P$502,3,FALSE) -> Spirit | E8: 118049.56 | F8: =E8/O8 -> 95.355057 | G8: 5453.58 | H8: 7894.77 | I8: 7650 | J8: 107958.37 | K8: Travel Points | L8: =VLOOKUP(B8,'✈ Flights (2)'!$A$2:$R$501,13,FALSE) -> 1000.42 | M8: =VLOOKUP(B8,'✈ Flights (2)'!$A$2:$R$501,16,FALSE) -> 118 | N8: =VLOOKUP(B8,'✈ Flights (2)'!$A$2:$R$501,14,FALSE) -> Business | O8: =VLOOKUP(B8,'✈ Flights (2)'!$A$2:$P$502,12,FALSE) -> 1238
A9: REV008 | B9: FL008 | C9: EWR | D9: =VLOOKUP(B9,'✈ Flights (2)'!$A$2:$P$502,3,FALSE) -> Southwest | E9: 44204.93 | F9: =E9/O9 -> 31.939978 | G9: 6270.19 | H9: 10678.53 | I9: 29227.75 | J9: 10568.84 | K9: Travel Points | L9: =VLOOKUP(B9,'✈ Flights (2)'!$A$2:$R$501,13,FALSE) -> 236.39 | M9: =VLOOKUP(B9,'✈ Flights (2)'!$A$2:$R$501,16,FALSE) -> 187 | N9: =VLOOKUP(B9,'✈ Flights (2)'!$A$2:$R$501,14,FALSE) -> First Class | O9: =VLOOKUP(B9,'✈ Flights (2)'!$A$2:$P$502,12,FALSE) -> 1384
A10: REV009 | B10: FL009 | C10: SFO | D10: =VLOOKUP(B10,'✈ Flights (2)'!$A$2:$P$502,3,FALSE) -> Spirit | E10: 93999.6 | F10: =E10/O10 -> 191.0561 | G10: 2430.02 | H10: 5604.74 | I10: 32325.6 | J10: 58499.28 | K10: Credit Card | L10: =VLOOKUP(B10,'✈ Flights (2)'!$A$2:$R$501,13,FALSE) -> 1044.44 | M10: =VLOOKUP(B10,'✈ Flights (2)'!$A$2:$R$501,16,FALSE) -> 90 | N10: =VLOOKUP(B10,'✈ Flights (2)'!$A$2:$R$501,14,FALSE) -> Economy | O10: =VLOOKUP(B10,'✈ Flights (2)'!$A$2:$P$502,12,FALSE) -> 492
A11: REV010 | B11: FL010 | C11: MSP | D11: =VLOOKUP(B11,'✈ Flights (2)'!$A$2:$P$502,3,FALSE) -> Spirit | E11: 109804.53 | F11: =E11/O11 -> 316.43957 | G11: 3370.99 | H11: 2780.76 | I11: 16642.92 | J11: 141386.35 | K11: Travel Points | L11: =VLOOKUP(B11,'✈ Flights (2)'!$A$2:$R$501,13,FALSE) -> 587.19 | M11: =VLOOKUP(B11,'✈ Flights (2)'!$A$2:$R$501,16,FALSE) -> 187 | N11: =VLOOKUP(B11,'✈ Flights (2)'!$A$2:$R$501,14,FALSE) -> Economy | O11: =VLOOKUP(B11,'✈ Flights (2)'!$A$2:$P$502,12,FALSE) -> 347
A12: REV011 | B12: FL011 | C12: LAS | D12: =VLOOKUP(B12,'✈ Flights (2)'!$A$2:$P$502,3,FALSE) -> United | E12: 45213.63 | F12: =E12/O12 -> 32.811052 | G12: 1834.47 | H12: 14732.49 | I12: 7428.95 | J12: 69648.3 | K12: Cash | L12: =VLOOKUP(B12,'✈ Flights (2)'!$A$2:$R$501,13,FALSE) -> 587.19 | M12: =VLOOKUP(B12,'✈ Flights (2)'!$A$2:$R$501,16,FALSE) -> 77 | N12: =VLOOKUP(B12,'✈ Flights (2)'!$A$2:$R$501,14,FALSE) -> Economy | O12: =VLOOKUP(B12,'✈ Flights (2)'!$A$2:$P$502,12,FALSE) -> 1378
A13: REV012 | B13: FL012 | C13: DFW | D13: =VLOOKUP(B13,'✈ Flights (2)'!$A$2:$P$502,3,FALSE) -> Southwest | E13: 116314.43 | F13: =E13/O13 -> 71.49012 | G13: 5077.26 | H13: 8396.74 | I13: 11245.48 | J13: 132836.44 | K13: Cash | L13: =VLOOKUP(B13,'✈ Flights (2)'!$A$2:$R$501,13,FALSE) -> 494.955 | M13: =VLOOKUP(B13,'✈ Flights (2)'!$A$2:$R$501,16,FALSE) -> 235 | N13: =VLOOKUP(B13,'✈ Flights (2)'!$A$2:$R$501,14,FALSE) -> Economy | O13: =VLOOKUP(B13,'✈ Flights (2)'!$A$2:$P$502,12,FALSE) -> 1627
... A501: REV500 | B501: FL500 | C501: MDW | D501: =VLOOKUP(B501,'✈ Flights (2)'!$A$2:$P$502,3,FALSE) -> Spirit | E501: 22404.72 | F501: =E501/O501 -> 21.626178 | G501: 3665.46 | H501: 4604.83 | I501: 11839.25 | J501: 9626.1 | K501: Cash | L501: =VLOOKUP(B501,'✈ Flights (2)'!$A$2:$R$501,13,FALSE) -> 430.86 | M501: =VLOOKUP(B501,'✈ Flights (2)'!$A$2:$R$501,16,FALSE) -> 52 | N501: =VLOOKUP(B501,'✈ Flights (2)'!$A$2:$R$501,14,FALSE) -> Economy | O501: =VLOOKUP(B501,'✈ Flights (2)'!$A$2:$P$502,12,FALSE) -> 1036
G504: Average Fuel Cost
U509: =VLOOKUP(B2,Flights!$A$2:$P$508,12,0)'

Sheet 📖 Data Dictionary
A1: 📖 DATA DICTIONARY — AIRLINE DATASET
A2: Table | B2: Column Name | C2: Data Type | D2: Valid Values / Range | E2: Description | F2: Contains Issues? | G2: Key Type | H2: Dirty Data Notes
A3: flights | B3: flight_id | C3: Text | D3: FL001–FL500 | E3: Unique identifier for each flight | F3: No | G3: Primary Key | H3: None
A4: flights | B4: flight_date | C4: Date | D4: 2022-01-01 to 2024-12-31 | E4: Date the flight was scheduled | F4: Yes (10 rows wrong format) | G4: – | H4: Check for DD/MM/YYYY vs YYYY-MM-DD
A5: flights | B5: airline | C5: Text | D5: Delta, United, American, Southwest, JetBlue, Alaska, Spirit, Frontier | E5: Airline operating the flight | F5: No | G5: – | H5: Some values in lowercase — standardize
A6: flights | B6: origin_city | C6: Text | D6: US city names | E6: City of departure | F6: No | G6: – | H6: None
A7: flights | B7: origin_code | C7: Text | D7: IATA 3-letter code | E7: Airport code of departure | F7: No | G7: Foreign Key → airports | H7: None
A8: flights | B8: destination_city | C8: Text | D8: US city names | E8: City of arrival | F8: No | G8: – | H8: None
A9: flights | B9: destination_code | C9: Text | D9: IATA 3-letter code | E9: Airport code of arrival | F9: No | G9: Foreign Key → airports | H9: None
A10: flights | B10: departure_time | C10: Text | D10: HH:MM (00:00–23:45) | E10: Scheduled departure time | F10: No | G10: – | H10: None
A11: flights | B11: arrival_time | C11: Text | D11: HH:MM (00:00–23:59) | E11: Scheduled arrival time | F11: No | G11: – | H11: None
A12: flights | B12: flight_duration_min | C12: Integer | D12: 90–480 | E12: Flight duration in minutes | F12: No | G12: – | H12: None
A13: flights | B13: distance_miles | C13: Integer | D13: 300–3000 | E13: Distance between origin and destination | F13: No | G13: – | H13: None
... A34: revenue | B34: payment_method | C34: Text | D34: Credit Card / Cash / Travel Points / Debit Card | E34: How ticket was paid | F34: No | G34: – | H34: None

Sheet 📝 Tasks
A1: 📝 STUDENT TASKS — DATA CLEANING, ANALYSIS, PIVOT TABLES & VISUALIZATION
A2: DATA CLEANING
A3: Task # | B3: Task | C3: Table | D3: Instructions
A4: DC-01 | B4: Fix inconsistent airline names (lowercase → Title Case) | C4: flights | D4: Use Find & Replace or a formula. All airline names should start with a capital letter. E.g. 'delta' → 'Delta'
A5: DC-02 | B5: Standardize the status column (UPPERCASE → Title Case) | C5: flights | D5: Values like 'ON-TIME' should be 'On-Time'. Use PROPER() or Find & Replace.
A6: DC-03 | B6: Fix date format inconsistencies | C6: flights | D6: Some dates are in DD/MM/YYYY format. Convert all to YYYY-MM-DD format.
A7: DC-04 | B7: Remove duplicate rows | C7: flights | D7: Identify and delete the 8 duplicate rows. Use Excel's 'Remove Duplicates' feature.
A8: DC-05 | B8: Handle missing ticket_price values | C8: flights | D8: Find blank cells in ticket_price. Replace with the median price per airline using MEDIAN() or fill manually.
A9: DC-06 | B9: Handle missing passengers_boarded values | C9: flights | D9: Replace missing values with the average passengers per class using AVERAGEIF().
A10: DC-07 | B10: Fix negative delay_minutes values | C10: flights | D10: Delay cannot be negative. Replace any negative delay with 0.
A11: DC-08 | B11: Fix outlier ticket prices | C11: flights | D11: Prices of -50, 0.5, 9999, and 15000 are likely errors. Replace with the average ticket price for the same class.
A12: DC-09 | B12: Handle missing fuel_cost in revenue | C12: revenue | D12: Fill missing fuel_cost values with the average fuel cost using AVERAGE().
A13: DC-10 | B13: Investigate zero total_revenue rows | C13: revenue | D13: Five rows have total_revenue = 0. Flag these rows and either correct or remove them.
A15: STATISTICAL ANALYSIS
A16: Task # | B16: Task | C16: Table | D16: Instructions
A17: SA-01 | B17: Calculate basic statistics for ticket_price | C17: flights | D17: Find the MIN, MAX, AVERAGE, MEDIAN, and STDEV of ticket_price. Use Excel functions.
A18: SA-02 | B18: Count flights by status | C18: flights | D18: Count how many flights are On-Time, Delayed, and Cancelled using COUNTIF().
A19: SA-03 | B19: Calculate average delay by airline | C19: flights | D19: Use AVERAGEIF() to find the average delay_minutes for each airline.
A20: SA-04 | B20: Find the busiest routes | C20: flights | D20: Combine origin_city and destination_city. Count occurrences to find the top 5 busiest routes.
A21: SA-05 | B21: Calculate average occupancy rate | C21: flights | D21: Occupancy = passengers_boarded / seats_available * 100. Create a new column and compute the average.
A22: SA-06 | B22: Find total and average profit by airline | C22: revenue | D22: Use SUMIF() and AVERAGEIF() to aggregate profit by airline (join via flight_id).
A23: SA-07 | B23: Calculate revenue per mile | C23: revenue | D23: Create a new column: revenue_per_mile = total_revenue / distance_miles (join flights table).
A24: SA-08 | B24: Find the airport with the most departures | C24: flights | D24: Count origin_code occurrences to find the top 3 busiest departure airports.
A26: PIVOT TABLES
A27: Task # | B27: Task | C27: Table | D27: Instructions
A28: PT-01 | B28: Flights by Airline and Status | C28: flights | D28: Create a pivot table showing count of flights for each airline, broken down by status (On-Time/Delayed/Cancelled).
A29: PT-02 | B29: Average Ticket Price by Class and Airline | C29: flights | D29: Rows = Airline, Columns = Class. Values = Average ticket_price.
A30: PT-03 | B30: Total Revenue by Airline | C30: revenue | D30: Join flights and revenue. Pivot total_revenue summed by airline.
A31: PT-04 | B31: Monthly Flight Count Trend | C31: flights | D31: Extract Month from flight_date. Rows = Month, Values = Count of flights.
A32: PT-05 | B32: Average Delay by Origin City | C32: flights | D32: Rows = origin_city. Values = Average delay_minutes. Sort descending.
A33: PT-06 | B33: Profit by Payment Method | C33: revenue | D33: Rows = payment_method. Values = SUM of profit. Sort by highest profit.
A35: DATA VISUALIZATION
A36: Task # | B36: Task | C36: Chart Type | D36: Instructions
A37: DV-01 | B37: Flight Status Distribution | C37: Pie Chart | D37: Show the proportion of On-Time vs Delayed vs Cancelled flights.
A38: DV-02 | B38: Average Ticket Price by Class | C38: Bar Chart | D38: Compare average ticket price across Economy, Business, and First Class.
A39: DV-03 | B39: Monthly Flights Over Time | C39: Line Chart | D39: Show how the number of flights changed month-by-month across 2022–2024.
A40: DV-04 | B40: Top 5 Airlines by Total Revenue | C40: Horizontal Bar Chart | D40: Rank airlines from highest to lowest total revenue.
A41: DV-05 | B41: Delay Minutes Distribution | C41: Histogram | D41: Show the distribution of delay_minutes to spot common delay ranges.
A42: DV-06 | B42: Occupancy Rate by Airline | C42: Column Chart | D42: Compare average occupancy rate (%) across airlines.
A43: DV-07 | B43: Profit vs Fuel Cost Scatter | C43: Scatter Plot | D43: Plot fuel_cost (x) vs profit (y) to identify any relationship.
A44: DV-08 | B44: Revenue Breakdown by Airport | C44: Stacked Bar Chart | D44: Show total_revenue vs ancillary_revenue for the top 8 airports.

Sheet Stat Analysis
A5: Calculate basic statistics for ticket_price | F5: Count flights by status | H5: Calculate average delay by airline | M5: Find the busiest routes
B8: Statistics | C8: Ticket Price | F8: Status | G8: Count | I8: Airline | J8: Average Delay
B9: Average (AVERAGE) | C9: =AVERAGE('✈ Flights (2)'!M2:M501) -> 619.22447 | F9: On-Time | G9: =COUNTIF('✈ Flights (2)'!$R$2:$R$501,"On-Time") -> 335 | I9: Delta | J9: =AVERAGEIF('✈ Flights (2)'!$C$2:$C$501,"Delta",'✈ Flights (2)'!T2:T501) -> 24.779661 | M9: Routes | N9: Count of Flight Id
B10: Median (MEDIAN) | C10: =MEDIAN('✈ Flights (2)'!M2:M501) -> 590.545 | F10: Delayed | G10: =COUNTIF('✈ Flights (2)'!$R$2:$R$501,"Delayed") -> 139 | I10: Southwest | J10: =AVERAGEIF('✈ Flights (2)'!$C$2:$C$501,"Southwest",'✈ Flights (2)'!T2:T501) -> 32 | M10: Chicago → Boston | N10: 7
B11: Std Deviation (STDEV) | C11: =STDEV('✈ Flights (2)'!M2:M501) -> 302.66384 | F11: Cancelled | G11: =COUNTIF('✈ Flights (2)'!$R$2:$R$501,"Cancelled") -> 26 | I11: Alaska | J11: =AVERAGEIF('✈ Flights (2)'!$C$2:$C$501,"Alaska",'✈ Flights (2)'!T2:T501) -> 25.754098 | M11: San Francisco → Minneapolis | N11: 5
B12: Minimum (MIN) | C12: =MIN('✈ Flights (2)'!M2:M501) -> 86.84 | I12: American | J12: =AVERAGEIF('✈ Flights (2)'!$C$2:$C$501,"American",'✈ Flights (2)'!T2:T501) -> 24.134328 | M12: San Diego → Chicago | N12: 5
B13: Maximum (MAX) | C13: =MAX('✈ Flights (2)'!M2:M501) -> 1196.58 | I13: Spirit | J13: =AVERAGEIF('✈ Flights (2)'!$C$2:$C$501,"Spirit",'✈ Flights (2)'!T2:T501) -> 31.686567 | M13: Houston → Las Vegas | N13: 5
I14: United | J14: =AVERAGEIF('✈ Flights (2)'!$C$2:$C$501,"United",'✈ Flights (2)'!T2:T501) -> 25.444444 | M14: Chicago → Detroit | N14: 5
A15: Calculate average occupancy rate | I15: Frontier | J15: =AVERAGEIF('✈ Flights (2)'!$C$2:$C$501,"Frontier",'✈ Flights (2)'!T2:T501) -> 18.8125 | M15: Charlotte → San Francisco | N15: 5
C16: =AVERAGE('✈ Flights (2)'!Q2:Q501) -> 62.326738 | I16: JetBlue | J16: =AVERAGEIF('✈ Flights (2)'!$C$2:$C$501,"JetBlue",'✈ Flights (2)'!T2:T501) -> 17.779661 | M16: Charlotte → Newark | N16: 5
M17: Newark → Houston | N17: 4
M18: New York → San Francisco | N18: 4
A19: Find total and average profit by airline | M19: Miami → Chicago | N19: 4
M20: Los Angeles → Phoenix | N20: 4
M21: Detroit → Chicago | N21: 4
M22: Denver → San Diego | N22: 4
M23: Denver → Houston | N23: 4
B24: Airline | C24: Total Profit | D24: Average Profit | M24: Dallas → Las Vegas | N24: 4
B25: Delta | C25: =SUMIF('💰 Revenue (2)'!$D$2:$D$502,B25,'💰 Revenue (2)'!$J$2:$J$502) -> 3416073.6 | D25: =AVERAGEIF('💰 Revenue (2)'!$D$2:$D$502,B25,'💰 Revenue (2)'!$J$2:$J$502) -> 57899.553 | M25: Chicago → Seattle | N25: 4
B26: Southwest | C26: =SUMIF('💰 Revenue (2)'!$D$2:$D$502,B26,'💰 Revenue (2)'!$J$2:$J$502) -> 4169184.8 | D26: =AVERAGEIF('💰 Revenue (2)'!$D$2:$D$502,B26,'💰 Revenue (2)'!$J$2:$J$502) -> 60422.968 | M26: Chicago → Los Angeles | N26: 4
B27: Alaska | C27: =SUMIF('💰 Revenue (2)'!$D$2:$D$502,B27,'💰 Revenue (2)'!$J$2:$J$502) -> 3712098 | D27: =AVERAGEIF('💰 Revenue (2)'!$D$2:$D$502,B27,'💰 Revenue (2)'!$J$2:$J$502) -> 60854.066 | F27: 6 | M27: Chicago → Atlanta | N27: 4
B28: American | C28: =SUMIF('💰 Revenue (2)'!$D$2:$D$502,B28,'💰 Revenue (2)'!$J$2:$J$502) -> 3141979 | D28: =AVERAGEIF('💰 Revenue (2)'!$D$2:$D$502,B28,'💰 Revenue (2)'!$J$2:$J$502) -> 46895.209 | G28: =AVERAGE('💰 Revenue (2)'!$F$2:$F$502) -> 69.596997 | M28: Boston → Newark | N28: 4
B29: Spirit | C29: =SUMIF('💰 Revenue (2)'!$D$2:$D$502,B29,'💰 Revenue (2)'!$J$2:$J$502) -> 4111871.5 | D29: =AVERAGEIF('💰 Revenue (2)'!$D$2:$D$502,B29,'💰 Revenue (2)'!$J$2:$J$502) -> 61371.217 | M29: Atlanta → New York | N29: 4
B30: United | C30: =SUMIF('💰 Revenue (2)'!$D$2:$D$502,B30,'💰 Revenue (2)'!$J$2:$J$502) -> 3426879.1 | D30: =AVERAGEIF('💰 Revenue (2)'!$D$2:$D$502,B30,'💰 Revenue (2)'!$J$2:$J$502) -> 63460.724 | M30: Atlanta → Chicago | N30: 4
B31: Frontier | C31: =SUMIF('💰 Revenue (2)'!$D$2:$D$502,B31,'💰 Revenue (2)'!$J$2:$J$502) -> 3299355.6 | D31: =AVERAGEIF('💰 Revenue (2)'!$D$2:$D$502,B31,'💰 Revenue (2)'!$J$2:$J$502) -> 51552.431 | G31: Find the airport with the most departures | M31: Atlanta → Charlotte | N31: 4
B32: JetBlue | C32: =SUMIF('💰 Revenue (2)'!$D$2:$D$502,B32,'💰 Revenue (2)'!$J$2:$J$502) -> 2910867.2 | D32: =AVERAGEIF('💰 Revenue (2)'!$D$2:$D$502,B32,'💰 Revenue (2)'!$J$2:$J$502) -> 49336.732 | F32: 7 | G32: ATL (Atlanta) — 35 departures | M32: Seattle → Orlando | N32: 3
G33: LAX (Los Angeles) — 32 departures | M33: Seattle → Chicago | N33: 3
G34: SAN (San Diego) — 30 departures | M34: San Francisco → Detroit | N34: 3
B35: average ticket price per class | M35: San Francisco → Chicago | N35: 3
M36: San Diego → Newark | N36: 3
B37: Class | C37: Average Price | M37: San Diego → Los Angeles | N37: 3
B38: Economy | C38: =AVERAGEIF('✈ Flights (2)'!$N$2:$N$501,"Economy",'✈ Flights (2)'!$M$2:$M$501) -> 586.99406 | M38: San Diego → Dallas | N38: 3
B39: Business | C39: =AVERAGEIF('✈ Flights (2)'!$N$2:$N$501,"Business",'✈ Flights (2)'!$M$2:$M$501) -> 624.39863 | M39: Phoenix → Atlanta | N39: 3
B40: First Class | C40: =AVERAGEIF('✈ Flights (2)'!$N$2:$N$501,"First Class",'✈ Flights (2)'!$M$2:$M$501) -> 634.1065 | M40: Orlando → San Francisco | N40: 3
M41: Orlando → Minneapolis | N41: 3
M42: Minneapolis → San Francisco | N42: 3
B43: Top 5 Airlines by Total Revenue | M43: Minneapolis → San Diego | N43: 3
M44: Minneapolis → Newark | N44: 3
B45: Airline | C45: Sum of Total Revenue | M45: Minneapolis → Chicago | N45: 3
B46: United | C46: 5204994.6 | M46: Miami → Houston | N46: 3
B47: American | C47: 5403300.8 | M47: Los Angeles → San Francisco | N47: 3
B48: Alaska | C48: 5660190.7 | M48: Los Angeles → Houston | N48: 3
B49: Spirit | C49: 6084130.6 | M49: Los Angeles → Denver | N49: 3
B50: Southwest | C50: 6470138.4 | M50: Los Angeles → Boston | N50: 3
M51: Las Vegas → New York | N51: 3
M52: Las Vegas → Los Angeles | N52: 3
B53: Delay Minutes | M53: Las Vegas → Boston | N53: 3
M54: Houston → San Diego | N54: 3
B55: Delay Range | C55: Count | M55: Houston → Dallas | N55: 3
B56: 0 Mins(No Delay) | C56: =COUNTIFS('✈ Flights (2)'!$T$2:$T$501,0) -> 367 | M56: Detroit → Miami | N56: 3
B57: 0-30 Mins | C57: =COUNTIFS('✈ Flights (2)'!$T$2:$T$501,">0",'✈ Flights (2)'!$T$2:$T$501,"<=30") -> 15 | M57: Denver → Chicago | N57: 3
B58: 31-60 Mins | C58: =COUNTIFS('✈ Flights (2)'!$T$2:$T$501,">30",'✈ Flights (2)'!$T$2:$T$501,"<=60") -> 27 | M58: Dallas → Houston | N58: 3
B59: 61-90 Mins | C59: =COUNTIFS('✈ Flights (2)'!$T$2:$T$501,">60",'✈ Flights (2)'!$T$2:$T$501,"<=90") -> 23 | M59: Chicago → San Francisco | N59: 3
B60: 91-120 Mins | C60: =COUNTIFS('✈ Flights (2)'!$T$2:$T$501,">90",'✈ Flights (2)'!$T$2:$T$501,"<=120") -> 23 | M60: Chicago → San Diego | N60: 3
B61: 121-150 Mins | C61: =COUNTIFS('✈ Flights (2)'!$T$2:$T$501,">120",'✈ Flights (2)'!$T$2:$T$501,"<=150") -> 21 | M61: Chicago → Phoenix | N61: 3
B62: 151-180 Mins | C62: =COUNTIFS('✈ Flights (2)'!$T$2:$T$501,">150",'✈ Flights (2)'!$T$2:$T$501,"<=180") -> 24 | M62: Chicago → Orlando | N62: 3
M63: Chicago → Newark | N63: 3
B64: Occupancy Rate by Airline — Column Chart | M64: Chicago → Minneapolis | N64: 3
M65: Chicago → Las Vegas | N65: 3
B66: Airline | C66: Avg Occupancy Rate % | M66: Charlotte → Los Angeles | N66: 3
B67: Southwest | C67: =AVERAGEIF('✈ Flights (2)'!$C$2:$C$501,"Southwest",'✈ Flights (2)'!$Q$2:$Q$501) -> 66.331759 | M67: Charlotte → Chicago | N67: 3
B68: Alaska | C68: =AVERAGEIF('✈ Flights (2)'!$C$2:$C$501,"Alaska",'✈ Flights (2)'!$Q$2:$Q$501) -> 64.463336 | M68: Boston → Los Angeles | N68: 3
B69: Delta | C69: =AVERAGEIF('✈ Flights (2)'!$C$2:$C$501,"Delta",'✈ Flights (2)'!$Q$2:$Q$501) -> 62.678598 | M69: Atlanta → Minneapolis | N69: 3
B70: Frontier | C70: =AVERAGEIF('✈ Flights (2)'!$C$2:$C$501,"Frontier",'✈ Flights (2)'!$Q$2:$Q$501) -> 62.068151 | M70: Atlanta → Miami | N70: 3
B71: American | C71: =AVERAGEIF('✈ Flights (2)'!$C$2:$C$501,"American",'✈ Flights (2)'!$Q$2:$Q$501) -> 61.67534 | M71: Seattle → San Francisco | N71: 2
B72: United | C72: =AVERAGEIF('✈ Flights (2)'!$C$2:$C$501,"United",'✈ Flights (2)'!$Q$2:$Q$501) -> 61.616338 | M72: Seattle → Newark | N72: 2
B73: Spirit | C73: =AVERAGEIF('✈ Flights (2)'!$C$2:$C$501,"Spirit",'✈ Flights (2)'!$Q$2:$Q$501) -> 60.596171 | M73: San Francisco → Phoenix | N73: 2
B74: JetBlue | C74: =AVERAGEIF('✈ Flights (2)'!$C$2:$C$501,"JetBlue",'✈ Flights (2)'!$Q$2:$Q$501) -> 58.717656 | M74: San Francisco → Orlando | N74: 2
M75: San Francisco → Houston | N75: 2
M76: San Francisco → Denver | N76: 2
B77: Revenue Breakdown by Airports | G77: Revenue Breakdown by Top 8 Airports | M77: San Francisco → Boston | N77: 2
M78: San Francisco → Atlanta | N78: 2
B79: Airport Code | C79: Airport Name | D79: Total Revenue | E79: Ancillary Revenue | G79: Airport Name | H79: Total Revenue | I79: Ancillary Revenue | M79: San Diego → New York | N79: 2
B80: ATL | C80: Hartsfield-Jackson Atlanta | D80: =SUMIF('💰 Revenue (2)'!$C$2:$C$501,B80,'💰 Revenue (2)'!$E$2:$E$501) -> 3387371 | E80: =SUMIF('💰 Revenue (2)'!$C$2:$C$501,B80,'💰 Revenue (2)'!$G$2:$G$501) -> 116115.5 | G80: Hartsfield-Jackson Atlanta | H80: 3387371 | I80: 116115.5 | M80: San Diego → Minneapolis | N80: 2
B81: CLT | C81: Charlotte Douglas International | D81: =SUMIF('💰 Revenue (2)'!$C$2:$C$501,B81,'💰 Revenue (2)'!$E$2:$E$501) -> 2946509.2 | E81: =SUMIF('💰 Revenue (2)'!$C$2:$C$501,B81,'💰 Revenue (2)'!$G$2:$G$501) -> 88849.48 | G81: Charlotte Douglas International | H81: 2946509.2 | I81: 88849.48 | M81: San Diego → Miami | N81: 2
B82: EWR | C82: Newark Liberty International | D82: =SUMIF('💰 Revenue (2)'!$C$2:$C$501,B82,'💰 Revenue (2)'!$E$2:$E$501) -> 2836290.7 | E82: =SUMIF('💰 Revenue (2)'!$C$2:$C$501,B82,'💰 Revenue (2)'!$G$2:$G$501) -> 91300.14 | G82: Newark Liberty International | H82: 2836290.7 | I82: 91300.14 | M82: San Diego → Houston | N82: 2
B83: LAX | C83: Los Angeles International | D83: =SUMIF('💰 Revenue (2)'!$C$2:$C$501,B83,'💰 Revenue (2)'!$E$2:$E$501) -> 2508592.4 | E83: =SUMIF('💰 Revenue (2)'!$C$2:$C$501,B83,'💰 Revenue (2)'!$G$2:$G$501) -> 118911.55 | G83: Los Angeles International | H83: 2508592.4 | I83: 118911.55 | M83: San Diego → Charlotte | N83: 2
B84: PHX | C84: Phoenix Sky Harbor | D84: =SUMIF('💰 Revenue (2)'!$C$2:$C$501,B84,'💰 Revenue (2)'!$E$2:$E$501) -> 2421244.6 | E84: =SUMIF('💰 Revenue (2)'!$C$2:$C$501,B84,'💰 Revenue (2)'!$G$2:$G$501) -> 112403.77 | G84: Phoenix Sky Harbor | H84: 2421244.6 | I84: 112403.77 | M84: Phoenix → Seattle | N84: 2
B85: MSP | C85: Minneapolis-Saint Paul | D85: =SUMIF('💰 Revenue (2)'!$C$2:$C$501,B85,'💰 Revenue (2)'!$E$2:$E$501) -> 2399597 | E85: =SUMIF('💰 Revenue (2)'!$C$2:$C$501,B85,'💰 Revenue (2)'!$G$2:$G$501) -> 101833.3 | G85: Minneapolis-Saint Paul | H85: 2399597 | I85: 101833.3 | M85: Phoenix → New York | N85: 2
B86: IAH | C86: George Bush Intercontinental | D86: =SUMIF('💰 Revenue (2)'!$C$2:$C$501,B86,'💰 Revenue (2)'!$E$2:$E$501) -> 2303107.1 | E86: =SUMIF('💰 Revenue (2)'!$C$2:$C$501,B86,'💰 Revenue (2)'!$G$2:$G$501) -> 92751.41 | G86: George Bush Intercontinental | H86: 2303107.1 | I86: 92751.41 | M86: Phoenix → Minneapolis | N86: 2
B87: SFO | C87: San Francisco International | D87: =SUMIF('💰 Revenue (2)'!$C$2:$C$501,B87,'💰 Revenue (2)'!$E$2:$E$501) -> 2210055.6 | E87: =SUMIF('💰 Revenue (2)'!$C$2:$C$501,B87,'💰 Revenue (2)'!$G$2:$G$501) -> 117783.71 | G87: San Francisco International | H87: 2210055.6 | I87: 117783.71 | M87: Phoenix → Los Angeles | N87: 2
B88: MDW | C88: Chicago Midway | D88: =SUMIF('💰 Revenue (2)'!$C$2:$C$501,B88,'💰 Revenue (2)'!$E$2:$E$501) -> 2203296.5 | E88: =SUMIF('💰 Revenue (2)'!$C$2:$C$501,B88,'💰 Revenue (2)'!$G$2:$G$501) -> 82667.12 | M88: Phoenix → Las Vegas | N88: 2
B89: SAN | C89: San Diego International | D89: =SUMIF('💰 Revenue (2)'!$C$2:$C$501,B89,'💰 Revenue (2)'!$E$2:$E$501) -> 2184158.7 | E89: =SUMIF('💰 Revenue (2)'!$C$2:$C$501,B89,'💰 Revenue (2)'!$G$2:$G$501) -> 140920.79 | M89: Phoenix → Houston | N89: 2
B90: DFW | C90: Dallas/Fort Worth International | D90: =SUMIF('💰 Revenue (2)'!$C$2:$C$501,B90,'💰 Revenue (2)'!$E$2:$E$501) -> 2154679.4 | E90: =SUMIF('💰 Revenue (2)'!$C$2:$C$501,B90,'💰 Revenue (2)'!$G$2:$G$501) -> 123044.56 | M90: Phoenix → Detroit | N90: 2
B91: BOS | C91: Logan International | D91: =SUMIF('💰 Revenue (2)'!$C$2:$C$501,B91,'💰 Revenue (2)'!$E$2:$E$501) -> 2077219.9 | E91: =SUMIF('💰 Revenue (2)'!$C$2:$C$501,B91,'💰 Revenue (2)'!$G$2:$G$501) -> 101226.16 | M91: Phoenix → Denver | N91: 2
B92: DTW | C92: Detroit Metropolitan | D92: =SUMIF('💰 Revenue (2)'!$C$2:$C$501,B92,'💰 Revenue (2)'!$E$2:$E$501) -> 2001775.7 | E92: =SUMIF('💰 Revenue (2)'!$C$2:$C$501,B92,'💰 Revenue (2)'!$G$2:$G$501) -> 124150.9 | M92: Phoenix → Chicago | N92: 2
B93: MIA | C93: Miami International | D93: =SUMIF('💰 Revenue (2)'!$C$2:$C$501,B93,'💰 Revenue (2)'!$E$2:$E$501) -> 1774604 | E93: =SUMIF('💰 Revenue (2)'!$C$2:$C$501,B93,'💰 Revenue (2)'!$G$2:$G$501) -> 85351.05 | M93: Phoenix → Boston | N93: 2
B94: JFK | C94: John F. Kennedy International | D94: =SUMIF('💰 Revenue (2)'!$C$2:$C$501,B94,'💰 Revenue (2)'!$E$2:$E$501) -> 1774397 | E94: =SUMIF('💰 Revenue (2)'!$C$2:$C$501,B94,'💰 Revenue (2)'!$G$2:$G$501) -> 97655.02 | M94: Orlando → San Diego | N94: 2
B95: MCO | C95: Orlando International | D95: =SUMIF('💰 Revenue (2)'!$C$2:$C$501,B95,'💰 Revenue (2)'!$E$2:$E$501) -> 1761505 | E95: =SUMIF('💰 Revenue (2)'!$C$2:$C$501,B95,'💰 Revenue (2)'!$G$2:$G$501) -> 83613.21 | M95: Orlando → Miami | N95: 2
B96: LAS | C96: Harry Reid International | D96: =SUMIF('💰 Revenue (2)'!$C$2:$C$501,B96,'💰 Revenue (2)'!$E$2:$E$501) -> 1706215.4 | E96: =SUMIF('💰 Revenue (2)'!$C$2:$C$501,B96,'💰 Revenue (2)'!$G$2:$G$501) -> 90757.7 | M96: Orlando → Detroit | N96: 2
B97: ORD | C97: O'Hare International | D97: =SUMIF('💰 Revenue (2)'!$C$2:$C$501,B97,'💰 Revenue (2)'!$E$2:$E$501) -> 1636955.6 | E97: =SUMIF('💰 Revenue (2)'!$C$2:$C$501,B97,'💰 Revenue (2)'!$G$2:$G$501) -> 85359.69 | M97: Orlando → Boston | N97: 2
B98: DEN | C98: Denver International | D98: =SUMIF('💰 Revenue (2)'!$C$2:$C$501,B98,'💰 Revenue (2)'!$E$2:$E$501) -> 1561724.4 | E98: =SUMIF('💰 Revenue (2)'!$C$2:$C$501,B98,'💰 Revenue (2)'!$G$2:$G$501) -> 94415.93 | M98: Newark → San Francisco | N98: 2
B99: SEA | C99: Seattle-Tacoma International | D99: =SUMIF('💰 Revenue (2)'!$C$2:$C$501,B99,'💰 Revenue (2)'!$E$2:$E$501) -> 1492093.3 | E99: =SUMIF('💰 Revenue (2)'!$C$2:$C$501,B99,'💰 Revenue (2)'!$G$2:$G$501) -> 56313.53 | M99: Newark → Orlando | N99: 2
M100: Newark → New York | N100: 2
M101: Newark → Minneapolis | N101: 2
M102: Newark → Los Angeles | N102: 2
M103: Newark → Las Vegas | N103: 2
M104: Newark → Dallas | N104: 2
M105: Newark → Boston | N105: 2
M106: New York → Phoenix | N106: 2
...

Sheet Pivot Tables
B2: Flights by Airline and Status
B5: Count of Flight Id | C5: Status
B6: Airline | C6: Cancelled | D6: Delayed | E6: On-Time
B7: Alaska | C7: 5 | D7: 15 | E7: 41
B8: American | C8: 6 | D8: 17 | E8: 44
B9: Delta | C9: 3 | D9: 17 | E9: 39
B10: Frontier | C10: 3 | D10: 16 | E10: 45
B11: Jetblue | C11: 1 | D11: 14 | E11: 44
B12: Southwest | C12: 3 | D12: 22 | E12: 44
B13: Spirit | C13: 2 | D13: 22 | E13: 43
B14: United | C14: 3 | D14: 16 | E14: 35
B19: Average Ticket Price by Class and Airline
B22: Average of Ticket Price | C22: Class
B23: Airline | C23: Business | D23: Economy | E23: First Class | F23: Unknown
B24: Alaska | C24: 588.10542 | D24: 651.575 | E24: 698.95376 | F24: 778.62667
B25: American | C25: 541.48442 | D25: 592.355 | E25: 592.22577 | F25: 637.648
B26: Delta | C26: 727.19395 | D26: 620.11133 | E26: 563.63543 | F26: 650.445
B27: Frontier | C27: 494.50313 | D27: 528.23924 | E27: 592.708 | F27: 765.79
B28: Jetblue | C28: 506.3875 | D28: 481.76389 | E28: 706.0313 | F28: 345.135
B29: Southwest | C29: 705.82045 | D29: 612.6366 | E29: 624.73875 | F29: 797.845
B30: Spirit | C30: 702.97252 | D30: 617.23211 | E30: 608.42706 | F30: 665.20333
B31: United | C31: 685.1283 | D31: 632.71167 | E31: 691.74429 | F31: 826.115
B41: Monthly Flight Count Trend
B46: Year-MONTH | C46: Count of Flight Id
B47: 2022-01 | C47: 12
B48: 2022-02 | C48: 11
B49: 2022-03 | C49: 17
B50: 2022-04 | C50: 17
B51: 2022-05 | C51: 11
B52: 2022-06 | C52: 18
B53: 2022-07 | C53: 21
B54: 2022-08 | C54: 14
B55: 2022-09 | C55: 14
B56: 2022-10 | C56: 18
B57: 2022-11 | C57: 15
B58: 2022-12 | C58: 12
... B82: 2024-12 | C82: 16
C86: Total Revenue by Airline
F89: Airline | G89: Sum of Total Revenue
F90: Southwest | G90: 6470138.4
F91: Spirit | G91: 6084130.6
F92: Alaska | G92: 5660190.7
F93: American | G93: 5403300.8
F94: United | G94: 5204994.6
F95: Delta | G95: 5187451.6
F96: Frontier | G96: 4942929.9
F97: Jetblue | G97: 4388255.9
F98: Grand Total | G98: 43341392
B108: Average Delay by Origin City
B113: Origin City | C113: Average of Delay Minutes
B114: San Francisco | C114: 45.535714
B115: Denver | C115: 43.5
B116: Dallas | C116: 42.583333
B117: Chicago | C117: 36.285714
B118: Newark | C118: 29.791667
B119: Las Vegas | C119: 29.681818
B120: Houston | C120: 28.238095
B121: Seattle | C121: 25.0625
B122: Los Angeles | C122: 24.0625
B123: Orlando | C123: 22.391304
B124: Miami | C124: 22.142857
B125: New York | C125: 21.269231
... B133: Grand Total | C133: 25.216
B136: Profit by Payment Method
B138: Payment Method | C138: Sum of Profit
B139: Credit Card | C139: 8269125
B140: Travel Points | C140: 7420488.9
B141: Cash | C141: 6640078.9
B142: Debit Card | C142: 5858616
B143: Grand Total | C143: 28188309

Sheet Visulization
B2: Flight Status Distribution — Pie Chart
C43: Monthly Flights Over Time — Line Chart
C65: Top 5 Airlines by Total Revenue
D84: Delay Minutes Distribution
D121: Profit vs Fuel Cost — Scatter Plot
C139: Revenue Breakdown by Top 8 Airports

Sheet Dashboard
D6: TOTAL FLIGHTS | G6: Total Revenue | K6: Avg Occupancy Rate | O6: Avg Delay
D7: =COUNTA('✈ Flights (2)'!$A$2:A$501) -> 500 | G7: =SUM('💰 Revenue (2)'!$E$2:$E$5) -> 436269.86 | K7: =AVERAGE('✈ Flights (2)'!$Q$2:$Q$501) -> 62.326738 | O7: =AVERAGE('✈ Flights (2)'!$T$2:$T$501) -> 25.216
